{
  "step": "2.7",
  "name": "cmb_frame_analysis",
  "timestamp": "2025-12-09T02:09:49.159966",
  "n_combinations_tested": 54,
  "best_result": {
    "filter": "dynamic_50",
    "mode": "multi_gnss",
    "metric": "pos_jitter",
    "coherence_type": "phase_alignment",
    "best_ra": 157.0,
    "best_dec": 9.0,
    "ra_ci_68": [
      150.0,
      190.0
    ],
    "dec_ci_68": [
      -10.0,
      40.0
    ],
    "correlation": 0.5625105978060736,
    "p_value": 0.00035579351075831767,
    "global_p_value": 0.007992007992007992,
    "corrected_p_value": 0.3516354895022673,
    "cmb_separation": 19.312029829443972,
    "apex_separation": 105.64584001969003
  },
  "methodology": {
    "grid_resolution_deg": 1,
    "background_speed_kms": 20.0,
    "bootstrap_samples": 500,
    "predictor": "cos(velocity_declination)"
  },
  "all_results": [
    {
      "filter": "dynamic_50",
      "mode": "multi_gnss",
      "metric": "pos_jitter",
      "coherence_type": "phase_alignment",
      "best_ra": 157.0,
      "best_dec": 9.0,
      "ra_ci_68": [
        150.0,
        190.0
      ],
      "dec_ci_68": [
        -10.0,
        40.0
      ],
      "correlation": 0.5625105978060736,
      "p_value": 0.00035579351075831767,
      "cmb_separation": 19.312029829443972,
      "apex_separation": 105.64584001969003
    },
    {
      "filter": "all_stations",
      "mode": "multi_gnss",
      "metric": "pos_jitter",
      "coherence_type": "phase_alignment",
      "best_ra": 188.0,
      "best_dec": -5.0,
      "ra_ci_68": [
        158.40000000000003,
        190.0
      ],
      "dec_ci_68": [
        -20.0,
        40.0
      ],
      "correlation": 0.5121178552128908,
      "p_value": 0.0014084608158764222,
      "cmb_separation": 20.043210090095354,
      "apex_separation": 86.47049920927512
    },
    {
      "filter": "dynamic_50",
      "mode": "ionofree",
      "metric": "clock_bias",
      "coherence_type": "phase_alignment",
      "best_ra": 180.0,
      "best_dec": -26.0,
      "ra_ci_68": [
        160.0,
        310.0
      ],
      "dec_ci_68": [
        -40.0,
        0.0
      ],
      "correlation": 0.14300077046576276,
      "p_value": 0.40540180340238186,
      "cmb_separation": 22.258323641475865,
      "apex_separation": 103.46021716763106
    },
    {
      "filter": "optimal_100",
      "mode": "ionofree",
      "metric": "clock_drift",
      "coherence_type": "msc",
      "best_ra": 200.0,
      "best_dec": -3.0,
      "ra_ci_68": [
        200.0,
        230.0
      ],
      "dec_ci_68": [
        -50.0,
        0.0
      ],
      "correlation": 0.3265039993404969,
      "p_value": 0.051953020801210004,
      "cmb_separation": 32.17193152448166,
      "apex_separation": 75.20295399008484
    },
    {
      "filter": "optimal_100",
      "mode": "ionofree",
      "metric": "clock_bias",
      "coherence_type": "msc",
      "best_ra": 200.0,
      "best_dec": 0.0,
      "ra_ci_68": [
        190.0,
        230.0
      ],
      "dec_ci_68": [
        -50.0,
        10.0
      ],
      "correlation": 0.25730392690120807,
      "p_value": 0.12977810717364124,
      "cmb_separation": 32.72411625752304,
      "apex_separation": 73.6233612007166
    },
    {
      "filter": "dynamic_50",
      "mode": "baseline",
      "metric": "clock_bias",
      "coherence_type": "phase_alignment",
      "best_ra": 171.0,
      "best_dec": 27.0,
      "ra_ci_68": [
        160.0,
        170.0
      ],
      "dec_ci_68": [
        20.0,
        40.0
      ],
      "correlation": 0.5248858929315691,
      "p_value": 0.0010139459922817728,
      "cmb_separation": 34.06919953248032,
      "apex_separation": 84.6636454629023
    },
    {
      "filter": "all_stations",
      "mode": "baseline",
      "metric": "clock_bias",
      "coherence_type": "phase_alignment",
      "best_ra": 171.0,
      "best_dec": 28.0,
      "ra_ci_68": [
        140.0,
        180.0
      ],
      "dec_ci_68": [
        20.0,
        40.0
      ],
      "correlation": 0.5083973195415494,
      "p_value": 0.001546339011506248,
      "cmb_separation": 35.06482767617924,
      "apex_separation": 84.14825079299742
    },
    {
      "filter": "optimal_100",
      "mode": "ionofree",
      "metric": "pos_jitter",
      "coherence_type": "phase_alignment",
      "best_ra": 176.0,
      "best_dec": 28.0,
      "ra_ci_68": [
        110.0,
        220.0
      ],
      "dec_ci_68": [
        10.0,
        40.0
      ],
      "correlation": 0.25598659740279184,
      "p_value": 0.13182324813220458,
      "cmb_separation": 35.797024155277974,
      "apex_separation": 80.3231148693597
    },
    {
      "filter": "all_stations",
      "mode": "ionofree",
      "metric": "clock_drift",
      "coherence_type": "msc",
      "best_ra": 179.0,
      "best_dec": 28.0,
      "ra_ci_68": [
        170.0,
        220.0
      ],
      "dec_ci_68": [
        -50.0,
        30.0
      ],
      "correlation": 0.22729927811944367,
      "p_value": 0.18246845883380858,
      "cmb_separation": 36.5369338757246,
      "apex_separation": 77.9919155786626
    },
    {
      "filter": "dynamic_50",
      "mode": "multi_gnss",
      "metric": "clock_bias",
      "coherence_type": "phase_alignment",
      "best_ra": 168.0,
      "best_dec": 30.0,
      "ra_ci_68": [
        80.0,
        170.0
      ],
      "dec_ci_68": [
        30.0,
        40.0
      ],
      "correlation": 0.48239092593627647,
      "p_value": 0.0028873121001056212,
      "cmb_separation": 36.940044939445606,
      "apex_separation": 85.33747035102907
    },
    {
      "filter": "all_stations",
      "mode": "multi_gnss",
      "metric": "clock_drift",
      "coherence_type": "phase_alignment",
      "best_ra": 181.0,
      "best_dec": 28.0,
      "ra_ci_68": [
        30.0,
        190.0
      ],
      "dec_ci_68": [
        20.0,
        40.0
      ],
      "correlation": 0.27885128415433574,
      "p_value": 0.09957599817244356,
      "cmb_separation": 37.147723711546334,
      "apex_separation": 76.42395149139631
    },
    {
      "filter": "dynamic_50",
      "mode": "multi_gnss",
      "metric": "clock_drift",
      "coherence_type": "phase_alignment",
      "best_ra": 176.0,
      "best_dec": 30.0,
      "ra_ci_68": [
        20.0,
        190.0
      ],
      "dec_ci_68": [
        20.0,
        40.0
      ],
      "correlation": 0.26832206231414124,
      "p_value": 0.11358408622032234,
      "cmb_separation": 37.74217442455772,
      "apex_separation": 79.36025249586054
    },
    {
      "filter": "optimal_100",
      "mode": "multi_gnss",
      "metric": "clock_drift",
      "coherence_type": "phase_alignment",
      "best_ra": 180.0,
      "best_dec": 29.0,
      "ra_ci_68": [
        90.0,
        230.0
      ],
      "dec_ci_68": [
        -30.0,
        40.0
      ],
      "correlation": 0.2298285012706159,
      "p_value": 0.17751806552342164,
      "cmb_separation": 37.77053750438462,
      "apex_separation": 76.75087010065505
    },
    {
      "filter": "all_stations",
      "mode": "multi_gnss",
      "metric": "clock_bias",
      "coherence_type": "phase_alignment",
      "best_ra": 168.0,
      "best_dec": 31.0,
      "ra_ci_68": [
        70.0,
        170.0
      ],
      "dec_ci_68": [
        30.0,
        50.0
      ],
      "correlation": 0.43747532373526,
      "p_value": 0.007626524989748251,
      "cmb_separation": 37.94004347727176,
      "apex_separation": 84.80581979217679
    },
    {
      "filter": "optimal_100",
      "mode": "multi_gnss",
      "metric": "pos_jitter",
      "coherence_type": "msc",
      "best_ra": 173.0,
      "best_dec": 31.0,
      "ra_ci_68": [
        170.0,
        210.0
      ],
      "dec_ci_68": [
        -50.0,
        30.0
      ],
      "correlation": 0.37731518452211865,
      "p_value": 0.023294060242990078,
      "cmb_separation": 38.24795436352528,
      "apex_separation": 81.12920057668404
    },
    {
      "filter": "optimal_100",
      "mode": "multi_gnss",
      "metric": "clock_drift",
      "coherence_type": "msc",
      "best_ra": 169.0,
      "best_dec": 32.0,
      "ra_ci_68": [
        160.0,
        170.0
      ],
      "dec_ci_68": [
        30.0,
        40.0
      ],
      "correlation": 0.3804323837382182,
      "p_value": 0.022087503775346295,
      "cmb_separation": 38.95313113747565,
      "apex_separation": 83.55422739035212
    },
    {
      "filter": "optimal_100",
      "mode": "multi_gnss",
      "metric": "clock_bias",
      "coherence_type": "msc",
      "best_ra": 170.0,
      "best_dec": 32.0,
      "ra_ci_68": [
        160.0,
        180.0
      ],
      "dec_ci_68": [
        20.0,
        40.0
      ],
      "correlation": 0.3504682991109618,
      "p_value": 0.03611951781658429,
      "cmb_separation": 38.98957010778442,
      "apex_separation": 82.82943365522999
    },
    {
      "filter": "all_stations",
      "mode": "multi_gnss",
      "metric": "clock_drift",
      "coherence_type": "msc",
      "best_ra": 171.0,
      "best_dec": 32.0,
      "ra_ci_68": [
        160.0,
        200.0
      ],
      "dec_ci_68": [
        -40.0,
        40.0
      ],
      "correlation": 0.43114867599723816,
      "p_value": 0.008657766754233576,
      "cmb_separation": 39.04929295402542,
      "apex_separation": 82.10101532100092
    },
    {
      "filter": "all_stations",
      "mode": "multi_gnss",
      "metric": "pos_jitter",
      "coherence_type": "msc",
      "best_ra": 172.0,
      "best_dec": 32.0,
      "ra_ci_68": [
        170.0,
        190.0
      ],
      "dec_ci_68": [
        0.0,
        30.0
      ],
      "correlation": 0.5488354223263474,
      "p_value": 0.0005280975070252047,
      "cmb_separation": 39.13219197401656,
      "apex_separation": 81.36905848417756
    },
    {
      "filter": "dynamic_50",
      "mode": "multi_gnss",
      "metric": "pos_jitter",
      "coherence_type": "msc",
      "best_ra": 172.0,
      "best_dec": 32.0,
      "ra_ci_68": [
        170.0,
        190.0
      ],
      "dec_ci_68": [
        10.0,
        40.0
      ],
      "correlation": 0.5674912549928587,
      "p_value": 0.000306804817699069,
      "cmb_separation": 39.13219197401656,
      "apex_separation": 81.36905848417756
    },
    {
      "filter": "all_stations",
      "mode": "baseline",
      "metric": "pos_jitter",
      "coherence_type": "msc",
      "best_ra": 173.0,
      "best_dec": 32.0,
      "ra_ci_68": [
        170.0,
        180.0
      ],
      "dec_ci_68": [
        30.0,
        40.0
      ],
      "correlation": 0.5848234390977611,
      "p_value": 0.00017980056759991925,
      "cmb_separation": 39.23811875274917,
      "apex_separation": 80.63364719797937
    },
    {
      "filter": "dynamic_50",
      "mode": "multi_gnss",
      "metric": "clock_drift",
      "coherence_type": "msc",
      "best_ra": 169.0,
      "best_dec": 33.0,
      "ra_ci_68": [
        160.0,
        200.0
      ],
      "dec_ci_68": [
        -40.0,
        40.0
      ],
      "correlation": 0.40625743053082203,
      "p_value": 0.013948295838135394,
      "cmb_separation": 39.95271340757911,
      "apex_separation": 83.03221982402081
    },
    {
      "filter": "dynamic_50",
      "mode": "baseline",
      "metric": "clock_drift",
      "coherence_type": "msc",
      "best_ra": 171.0,
      "best_dec": 33.0,
      "ra_ci_68": [
        170.0,
        180.0
      ],
      "dec_ci_68": [
        30.0,
        40.0
      ],
      "correlation": 0.49759013361801224,
      "p_value": 0.00201637665379395,
      "cmb_separation": 40.04582330232471,
      "apex_separation": 81.5933928757133
    },
    {
      "filter": "dynamic_50",
      "mode": "baseline",
      "metric": "pos_jitter",
      "coherence_type": "msc",
      "best_ra": 172.0,
      "best_dec": 33.0,
      "ra_ci_68": [
        170.0,
        180.0
      ],
      "dec_ci_68": [
        30.0,
        40.0
      ],
      "correlation": 0.5382468993435845,
      "p_value": 0.0007088587988657302,
      "cmb_separation": 40.126101438918965,
      "apex_separation": 80.86857566761017
    },
    {
      "filter": "all_stations",
      "mode": "baseline",
      "metric": "clock_drift",
      "coherence_type": "phase_alignment",
      "best_ra": 180.0,
      "best_dec": 32.0,
      "ra_ci_68": [
        20.0,
        190.0
      ],
      "dec_ci_68": [
        20.0,
        40.0
      ],
      "correlation": 0.30176514548601424,
      "p_value": 0.07367117557739333,
      "cmb_separation": 40.604102224540966,
      "apex_separation": 75.39569661849659
    },
    {
      "filter": "dynamic_50",
      "mode": "multi_gnss",
      "metric": "clock_bias",
      "coherence_type": "msc",
      "best_ra": 169.0,
      "best_dec": 34.0,
      "ra_ci_68": [
        170.0,
        200.0
      ],
      "dec_ci_68": [
        -40.0,
        40.0
      ],
      "correlation": 0.4266858623687244,
      "p_value": 0.009454796693077139,
      "cmb_separation": 40.95231272743029,
      "apex_separation": 82.51176579773743
    },
    {
      "filter": "all_stations",
      "mode": "multi_gnss",
      "metric": "clock_bias",
      "coherence_type": "msc",
      "best_ra": 170.0,
      "best_dec": 34.0,
      "ra_ci_68": [
        160.0,
        200.0
      ],
      "dec_ci_68": [
        -40.0,
        40.0
      ],
      "correlation": 0.4246971909315699,
      "p_value": 0.009829595435826288,
      "cmb_separation": 40.986482917202665,
      "apex_separation": 81.80157211769627
    },
    {
      "filter": "optimal_100",
      "mode": "multi_gnss",
      "metric": "clock_bias",
      "coherence_type": "phase_alignment",
      "best_ra": 170.0,
      "best_dec": 34.0,
      "ra_ci_68": [
        160.0,
        210.0
      ],
      "dec_ci_68": [
        -40.0,
        40.0
      ],
      "correlation": 0.2540062843020193,
      "p_value": 0.1349424006025166,
      "cmb_separation": 40.986482917202665,
      "apex_separation": 81.80157211769627
    },
    {
      "filter": "dynamic_50",
      "mode": "baseline",
      "metric": "clock_bias",
      "coherence_type": "msc",
      "best_ra": 170.0,
      "best_dec": 34.0,
      "ra_ci_68": [
        160.0,
        190.0
      ],
      "dec_ci_68": [
        10.0,
        40.0
      ],
      "correlation": 0.5018525023306103,
      "p_value": 0.0018178473513654758,
      "cmb_separation": 40.986482917202665,
      "apex_separation": 81.80157211769627
    },
    {
      "filter": "optimal_100",
      "mode": "baseline",
      "metric": "clock_bias",
      "coherence_type": "msc",
      "best_ra": 172.0,
      "best_dec": 34.0,
      "ra_ci_68": [
        160.0,
        210.0
      ],
      "dec_ci_68": [
        -40.0,
        40.0
      ],
      "correlation": 0.3769119481557124,
      "p_value": 0.023454054659864942,
      "cmb_separation": 41.12025732512005,
      "apex_separation": 80.37019849685211
    },
    {
      "filter": "dynamic_50",
      "mode": "baseline",
      "metric": "clock_drift",
      "coherence_type": "phase_alignment",
      "best_ra": 175.0,
      "best_dec": 34.0,
      "ra_ci_68": [
        10.0,
        190.0
      ],
      "dec_ci_68": [
        20.0,
        40.0
      ],
      "correlation": 0.29606391864753695,
      "p_value": 0.07956123637608425,
      "cmb_separation": 41.482638557580316,
      "apex_separation": 78.1969357861017
    },
    {
      "filter": "all_stations",
      "mode": "baseline",
      "metric": "clock_drift",
      "coherence_type": "msc",
      "best_ra": 169.0,
      "best_dec": 35.0,
      "ra_ci_68": [
        160.0,
        180.0
      ],
      "dec_ci_68": [
        30.0,
        40.0
      ],
      "correlation": 0.5290546445164752,
      "p_value": 0.0009082292665152369,
      "cmb_separation": 41.95192784462804,
      "apex_separation": 81.99298649145842
    },
    {
      "filter": "optimal_100",
      "mode": "baseline",
      "metric": "pos_jitter",
      "coherence_type": "phase_alignment",
      "best_ra": 165.0,
      "best_dec": 35.0,
      "ra_ci_68": [
        10.0,
        170.0
      ],
      "dec_ci_68": [
        30.0,
        40.0
      ],
      "correlation": 0.42134634099522283,
      "p_value": 0.010489712625272096,
      "cmb_separation": 42.031669739163185,
      "apex_separation": 84.7645179972556
    },
    {
      "filter": "optimal_100",
      "mode": "baseline",
      "metric": "clock_drift",
      "coherence_type": "msc",
      "best_ra": 171.0,
      "best_dec": 35.0,
      "ra_ci_68": [
        160.0,
        210.0
      ],
      "dec_ci_68": [
        -40.0,
        40.0
      ],
      "correlation": 0.3721105693028921,
      "p_value": 0.025430104290302014,
      "cmb_separation": 42.0392965459225,
      "apex_separation": 80.58402224847588
    },
    {
      "filter": "all_stations",
      "mode": "baseline",
      "metric": "clock_bias",
      "coherence_type": "msc",
      "best_ra": 168.0,
      "best_dec": 36.0,
      "ra_ci_68": [
        160.0,
        180.0
      ],
      "dec_ci_68": [
        30.0,
        40.0
      ],
      "correlation": 0.5450254168952442,
      "p_value": 0.0005877632053599147,
      "cmb_separation": 42.940037035526515,
      "apex_separation": 82.16704894920954
    },
    {
      "filter": "optimal_100",
      "mode": "baseline",
      "metric": "clock_bias",
      "coherence_type": "phase_alignment",
      "best_ra": 165.0,
      "best_dec": 36.0,
      "ra_ci_68": [
        150.0,
        190.0
      ],
      "dec_ci_68": [
        20.0,
        40.0
      ],
      "correlation": 0.3754379724791047,
      "p_value": 0.024046660609182924,
      "cmb_separation": 43.028828867931274,
      "apex_separation": 84.21631346658063
    },
    {
      "filter": "optimal_100",
      "mode": "baseline",
      "metric": "pos_jitter",
      "coherence_type": "msc",
      "best_ra": 169.0,
      "best_dec": 38.0,
      "ra_ci_68": [
        160.0,
        190.0
      ],
      "dec_ci_68": [
        0.0,
        40.0
      ],
      "correlation": 0.4626295267621848,
      "p_value": 0.004497500402742105,
      "cmb_separation": 44.95085710920477,
      "apex_separation": 80.44792004679921
    },
    {
      "filter": "optimal_100",
      "mode": "multi_gnss",
      "metric": "pos_jitter",
      "coherence_type": "phase_alignment",
      "best_ra": 159.0,
      "best_dec": 38.0,
      "ra_ci_68": [
        150.0,
        200.0
      ],
      "dec_ci_68": [
        -40.0,
        40.0
      ],
      "correlation": 0.2523562237992891,
      "p_value": 0.13758270434289765,
      "cmb_separation": 45.70571003397665,
      "apex_separation": 87.00864872169096
    },
    {
      "filter": "dynamic_50",
      "mode": "ionofree",
      "metric": "clock_drift",
      "coherence_type": "msc",
      "best_ra": 213.0,
      "best_dec": -46.0,
      "ra_ci_68": [
        170.0,
        220.0
      ],
      "dec_ci_68": [
        -50.0,
        30.0
      ],
      "correlation": 0.2807347185002512,
      "p_value": 0.09721555437024554,
      "cmb_separation": 54.96997532779421,
      "apex_separation": 92.3426072097838
    },
    {
      "filter": "all_stations",
      "mode": "baseline",
      "metric": "pos_jitter",
      "coherence_type": "phase_alignment",
      "best_ra": 149.0,
      "best_dec": 46.0,
      "ra_ci_68": [
        140.0,
        180.0
      ],
      "dec_ci_68": [
        10.0,
        50.0
      ],
      "correlation": 0.482631399757208,
      "p_value": 0.002871318798540967,
      "cmb_separation": 55.57568764368553,
      "apex_separation": 87.65739279021619
    },
    {
      "filter": "all_stations",
      "mode": "ionofree",
      "metric": "clock_bias",
      "coherence_type": "msc",
      "best_ra": 215.0,
      "best_dec": -47.0,
      "ra_ci_68": [
        170.0,
        230.0
      ],
      "dec_ci_68": [
        -50.0,
        30.0
      ],
      "correlation": 0.2764657664340631,
      "p_value": 0.10262805236550188,
      "cmb_separation": 56.662855148840556,
      "apex_separation": 92.02880440093655
    },
    {
      "filter": "dynamic_50",
      "mode": "ionofree",
      "metric": "clock_bias",
      "coherence_type": "msc",
      "best_ra": 215.0,
      "best_dec": -47.0,
      "ra_ci_68": [
        180.0,
        230.0
      ],
      "dec_ci_68": [
        -50.0,
        30.0
      ],
      "correlation": 0.3224298673505064,
      "p_value": 0.05512662401479407,
      "cmb_separation": 56.662855148840556,
      "apex_separation": 92.02880440093655
    },
    {
      "filter": "dynamic_50",
      "mode": "ionofree",
      "metric": "pos_jitter",
      "coherence_type": "msc",
      "best_ra": 217.0,
      "best_dec": -48.0,
      "ra_ci_68": [
        210.0,
        230.0
      ],
      "dec_ci_68": [
        -50.0,
        -30.0
      ],
      "correlation": 0.4393994304450466,
      "p_value": 0.007334541336533107,
      "cmb_separation": 58.32894893749166,
      "apex_separation": 91.77417246047867
    },
    {
      "filter": "optimal_100",
      "mode": "ionofree",
      "metric": "clock_drift",
      "coherence_type": "phase_alignment",
      "best_ra": 115.0,
      "best_dec": 22.0,
      "ra_ci_68": [
        20.0,
        340.0
      ],
      "dec_ci_68": [
        0.0,
        30.0
      ],
      "correlation": 0.20294890212452915,
      "p_value": 0.23517956630316972,
      "cmb_separation": 59.375418022051036,
      "apex_separation": 123.10954589118657
    },
    {
      "filter": "all_stations",
      "mode": "ionofree",
      "metric": "pos_jitter",
      "coherence_type": "msc",
      "best_ra": 219.0,
      "best_dec": -48.0,
      "ra_ci_68": [
        210.0,
        230.0
      ],
      "dec_ci_68": [
        -50.0,
        -38.40000000000032
      ],
      "correlation": 0.47531276070732426,
      "p_value": 0.0033941622225674983,
      "cmb_separation": 59.51813899508932,
      "apex_separation": 90.84837377525966
    },
    {
      "filter": "dynamic_50",
      "mode": "baseline",
      "metric": "pos_jitter",
      "coherence_type": "phase_alignment",
      "best_ra": 144.0,
      "best_dec": 49.0,
      "ra_ci_68": [
        130.0,
        170.0
      ],
      "dec_ci_68": [
        10.0,
        50.0
      ],
      "correlation": 0.49038776811801105,
      "p_value": 0.0023951896769753844,
      "cmb_separation": 59.73274440649708,
      "apex_separation": 87.96985571396755
    },
    {
      "filter": "optimal_100",
      "mode": "ionofree",
      "metric": "pos_jitter",
      "coherence_type": "msc",
      "best_ra": 112.0,
      "best_dec": 20.0,
      "ra_ci_68": [
        30.0,
        120.0
      ],
      "dec_ci_68": [
        10.0,
        20.0
      ],
      "correlation": 0.31433392762327184,
      "p_value": 0.061890133909591416,
      "cmb_separation": 61.24255138297166,
      "apex_separation": 126.0673277498421
    },
    {
      "filter": "dynamic_50",
      "mode": "ionofree",
      "metric": "clock_drift",
      "coherence_type": "phase_alignment",
      "best_ra": 92.0,
      "best_dec": 29.0,
      "ra_ci_68": [
        70.0,
        320.0
      ],
      "dec_ci_68": [
        10.0,
        30.0
      ],
      "correlation": 0.3391138346775819,
      "p_value": 0.043045245456367676,
      "cmb_separation": 81.23732868306644,
      "apex_separation": 120.99228913526039
    },
    {
      "filter": "all_stations",
      "mode": "ionofree",
      "metric": "clock_drift",
      "coherence_type": "phase_alignment",
      "best_ra": 91.0,
      "best_dec": 32.0,
      "ra_ci_68": [
        60.0,
        300.0
      ],
      "dec_ci_68": [
        10.0,
        40.0
      ],
      "correlation": 0.40851386668225287,
      "p_value": 0.01337695959018892,
      "cmb_separation": 82.7499187883643,
      "apex_separation": 118.00000000000001
    },
    {
      "filter": "optimal_100",
      "mode": "baseline",
      "metric": "clock_drift",
      "coherence_type": "phase_alignment",
      "best_ra": 94.0,
      "best_dec": 42.0,
      "ra_ci_68": [
        60.0,
        200.0
      ],
      "dec_ci_68": [
        20.0,
        50.0
      ],
      "correlation": 0.4504833972406236,
      "p_value": 0.0058321790346897995,
      "cmb_separation": 82.92149560177182,
      "apex_separation": 107.94687204893003
    },
    {
      "filter": "dynamic_50",
      "mode": "ionofree",
      "metric": "pos_jitter",
      "coherence_type": "phase_alignment",
      "best_ra": 14.0,
      "best_dec": 34.0,
      "ra_ci_68": [
        10.0,
        201.59999999999968
      ],
      "dec_ci_68": [
        -40.0,
        40.0
      ],
      "correlation": 0.1819626393662707,
      "p_value": 0.28817030329569726,
      "cmb_separation": 143.79062132032013,
      "apex_separation": 83.21818058167314
    },
    {
      "filter": "all_stations",
      "mode": "ionofree",
      "metric": "pos_jitter",
      "coherence_type": "phase_alignment",
      "best_ra": 12.0,
      "best_dec": 34.0,
      "ra_ci_68": [
        10.0,
        311.5999999999997
      ],
      "dec_ci_68": [
        -40.0,
        40.0
      ],
      "correlation": 0.2138737062091823,
      "p_value": 0.21038501449021885,
      "cmb_separation": 144.987885840784,
      "apex_separation": 81.80157211769632
    },
    {
      "filter": "all_stations",
      "mode": "ionofree",
      "metric": "clock_bias",
      "coherence_type": "phase_alignment",
      "best_ra": 318.0,
      "best_dec": -6.0,
      "ra_ci_68": [
        170.0,
        320.0
      ],
      "dec_ci_68": [
        -40.0,
        0.0
      ],
      "correlation": 0.1207052105881302,
      "p_value": 0.48315178614858656,
      "cmb_separation": 147.44306354873686,
      "apex_separation": 57.64739721337764
    },
    {
      "filter": "optimal_100",
      "mode": "ionofree",
      "metric": "clock_bias",
      "coherence_type": "phase_alignment",
      "best_ra": 16.0,
      "best_dec": 7.0,
      "ra_ci_68": [
        20.0,
        330.0
      ],
      "dec_ci_68": [
        -40.0,
        20.0
      ],
      "correlation": 0.302971484160369,
      "p_value": 0.0724696913717553,
      "cmb_separation": 152.15150285536376,
      "apex_separation": 99.29620533777577
    }
  ],
  "cmb_dipole": {
    "name": "CMB Dipole",
    "ra": 167.94,
    "dec": -6.94,
    "speed_kms": 369.82
  },
  "solar_apex": {
    "name": "Solar Apex",
    "ra": 271.0,
    "dec": 30.0,
    "speed_kms": 20.0
  },
  "comparison_to_code": {
    "code_ra": 186,
    "code_dec": -4,
    "code_cmb_sep": 18.2,
    "code_variance_ratio": 5570,
    "best_rinex_cmb_sep": 19.312029829443972
  }
}