{
  "filter": "DYNAMIC_50",
  "filter_config": "dynamic_50_metadata.json",
  "filter_metadata": {
    "type": "metadata",
    "file": "dynamic_50_metadata.json",
    "n_stations": 400,
    "n_north": 290,
    "n_south": 110,
    "hemisphere_ratio": "290:110"
  },
  "processing_mode": "baseline",
  "mode_description": "SPP with Broadcast Ephemeris",
  "results": {
    "clock_bias": {
      "msc": {
        "monthly_anisotropy": {
          "2022-01": {
            "year": 2022,
            "month": 1,
            "ratio": 1.053003934300659,
            "velocity": 30.266752889009627,
            "ew_lambda": 636.1777628947847,
            "ns_lambda": 604.1551623615682,
            "ew_r2": 0.9477819227107984,
            "ns_r2": 0.9752704499662804,
            "n_ew_pairs": 186899,
            "n_ns_pairs": 192012
          },
          "2022-02": {
            "year": 2022,
            "month": 2,
            "ratio": 1.0052045397917897,
            "velocity": 30.152908164805467,
            "ew_lambda": 668.6745753562565,
            "ns_lambda": 665.2124506866637,
            "ew_r2": 0.955011750936433,
            "ns_r2": 0.96807161182813,
            "n_ew_pairs": 157869,
            "n_ns_pairs": 166222
          },
          "2022-03": {
            "year": 2022,
            "month": 3,
            "ratio": 1.2182178596478637,
            "velocity": 29.941801077621474,
            "ew_lambda": 809.8912335858104,
            "ns_lambda": 664.8164178285125,
            "ew_r2": 0.9590877968954624,
            "ns_r2": 0.9627831115635461,
            "n_ew_pairs": 191744,
            "n_ns_pairs": 193856
          },
          "2022-04": {
            "year": 2022,
            "month": 4,
            "ratio": 1.2813428137812841,
            "velocity": 29.688492835763494,
            "ew_lambda": 853.8506529321422,
            "ns_lambda": 666.3717498148691,
            "ew_r2": 0.941717286029034,
            "ns_r2": 0.9131565267763871,
            "n_ew_pairs": 179335,
            "n_ns_pairs": 187021
          },
          "2022-05": {
            "year": 2022,
            "month": 5,
            "ratio": 1.1108370406881505,
            "velocity": 29.459051604240003,
            "ew_lambda": 756.8418979049541,
            "ns_lambda": 681.3257662312911,
            "ew_r2": 0.9511554133684857,
            "ns_r2": 0.9285805943736336,
            "n_ew_pairs": 185511,
            "n_ns_pairs": 207682
          },
          "2022-06": {
            "year": 2022,
            "month": 6,
            "ratio": 0.9940773566290081,
            "velocity": 29.31332052527508,
            "ew_lambda": 804.8677673310448,
            "ns_lambda": 809.6631132011825,
            "ew_r2": 0.9722269563775405,
            "ns_r2": 0.9626855818302021,
            "n_ew_pairs": 258765,
            "n_ns_pairs": 262049
          },
          "2022-07": {
            "year": 2022,
            "month": 7,
            "ratio": 1.1051816227213214,
            "velocity": 29.289309356866724,
            "ew_lambda": 916.1566395496109,
            "ns_lambda": 828.9647789236046,
            "ew_r2": 0.9647057367852168,
            "ns_r2": 0.9702705139315395,
            "n_ew_pairs": 206095,
            "n_ns_pairs": 211006
          },
          "2022-08": {
            "year": 2022,
            "month": 8,
            "ratio": 1.2334092859092012,
            "velocity": 29.393280721284196,
            "ew_lambda": 985.4745273886343,
            "ns_lambda": 798.9841966060739,
            "ew_r2": 0.9615647363748981,
            "ns_r2": 0.9673164193101655,
            "n_ew_pairs": 206793,
            "n_ns_pairs": 213789
          },
          "2022-09": {
            "year": 2022,
            "month": 9,
            "ratio": 1.3621813520174595,
            "velocity": 29.598116680279198,
            "ew_lambda": 868.5171763283757,
            "ns_lambda": 637.5929130449906,
            "ew_r2": 0.9621829839537461,
            "ns_r2": 0.9751434459126362,
            "n_ew_pairs": 196629,
            "n_ns_pairs": 204525
          },
          "2022-10": {
            "year": 2022,
            "month": 10,
            "ratio": 1.23911029420527,
            "velocity": 29.85039166885911,
            "ew_lambda": 768.2775581391121,
            "ns_lambda": 620.0235457101609,
            "ew_r2": 0.9616179189311043,
            "ns_r2": 0.9498129302107448,
            "n_ew_pairs": 176817,
            "n_ns_pairs": 193359
          },
          "2022-11": {
            "year": 2022,
            "month": 11,
            "ratio": 1.239204751477263,
            "velocity": 30.084307016397368,
            "ew_lambda": 762.3609944434108,
            "ns_lambda": 615.2018006181754,
            "ew_r2": 0.9659728352953729,
            "ns_r2": 0.9659210472410922,
            "n_ew_pairs": 176894,
            "n_ns_pairs": 185830
          },
          "2022-12": {
            "year": 2022,
            "month": 12,
            "ratio": 0.8506112957555458,
            "velocity": 30.23885263626665,
            "ew_lambda": 754.5235974756513,
            "ns_lambda": 887.0368889299245,
            "ew_r2": 0.9572726446995766,
            "ns_r2": 0.9433694202851383,
            "n_ew_pairs": 180852,
            "n_ns_pairs": 185246
          },
          "2023-01": {
            "year": 2023,
            "month": 1,
            "ratio": 0.8155120046098316,
            "velocity": 30.266752889009627,
            "ew_lambda": 821.0499424834303,
            "ns_lambda": 1006.7907496668282,
            "ew_r2": 0.9596456813613758,
            "ns_r2": 0.9372042692454807,
            "n_ew_pairs": 174368,
            "n_ns_pairs": 177259
          },
          "2023-02": {
            "year": 2023,
            "month": 2,
            "ratio": 1.1135093322208698,
            "velocity": 30.152908164805467,
            "ew_lambda": 677.1152723291956,
            "ns_lambda": 608.0912415693042,
            "ew_r2": 0.9629039026687993,
            "ns_r2": 0.9561252765744743,
            "n_ew_pairs": 155946,
            "n_ns_pairs": 163652
          },
          "2023-03": {
            "year": 2023,
            "month": 3,
            "ratio": 1.3654161058409358,
            "velocity": 29.941801077621474,
            "ew_lambda": 750.2656319642301,
            "ns_lambda": 549.4776491611359,
            "ew_r2": 0.9690455548746801,
            "ns_r2": 0.9642800375603406,
            "n_ew_pairs": 149067,
            "n_ns_pairs": 167098
          },
          "2023-04": {
            "year": 2023,
            "month": 4,
            "ratio": 1.2156524959021553,
            "velocity": 29.688492835763494,
            "ew_lambda": 742.3038931137802,
            "ns_lambda": 610.6217818134816,
            "ew_r2": 0.969556374184695,
            "ns_r2": 0.9462290667154087,
            "n_ew_pairs": 160574,
            "n_ns_pairs": 174909
          },
          "2023-05": {
            "year": 2023,
            "month": 5,
            "ratio": 1.299016473464835,
            "velocity": 29.459051604240003,
            "ew_lambda": 904.8478872069776,
            "ns_lambda": 696.5638278577783,
            "ew_r2": 0.9597179598551262,
            "ns_r2": 0.9520589714374401,
            "n_ew_pairs": 194088,
            "n_ns_pairs": 195004
          },
          "2023-06": {
            "year": 2023,
            "month": 6,
            "ratio": 1.1388449820902957,
            "velocity": 29.31332052527508,
            "ew_lambda": 806.3432967768239,
            "ns_lambda": 708.0360448151769,
            "ew_r2": 0.9626306710923693,
            "ns_r2": 0.9715558762934052,
            "n_ew_pairs": 205395,
            "n_ns_pairs": 209179
          },
          "2023-07": {
            "year": 2023,
            "month": 7,
            "ratio": 1.2603929646361205,
            "velocity": 29.289309356866724,
            "ew_lambda": 1151.6135976391367,
            "ns_lambda": 913.6940858533047,
            "ew_r2": 0.9553839484397408,
            "ns_r2": 0.9712095951403457,
            "n_ew_pairs": 213008,
            "n_ns_pairs": 214576
          },
          "2023-08": {
            "year": 2023,
            "month": 8,
            "ratio": 1.3373969241337553,
            "velocity": 29.393280721284196,
            "ew_lambda": 933.0128122005968,
            "ns_lambda": 697.6334365393566,
            "ew_r2": 0.9668759199540187,
            "ns_r2": 0.971940172702059,
            "n_ew_pairs": 198275,
            "n_ns_pairs": 203089
          },
          "2023-09": {
            "year": 2023,
            "month": 9,
            "ratio": 1.2238058495719712,
            "velocity": 29.598116680279198,
            "ew_lambda": 796.8141926468734,
            "ns_lambda": 651.0952639469414,
            "ew_r2": 0.9837089915371531,
            "ns_r2": 0.9724836470575083,
            "n_ew_pairs": 177003,
            "n_ns_pairs": 191794
          },
          "2023-10": {
            "year": 2023,
            "month": 10,
            "ratio": 1.2680854405423976,
            "velocity": 29.85039166885911,
            "ew_lambda": 800.4323100671805,
            "ns_lambda": 631.2132325443403,
            "ew_r2": 0.9755820044682609,
            "ns_r2": 0.9737212089164018,
            "n_ew_pairs": 167537,
            "n_ns_pairs": 185897
          },
          "2023-11": {
            "year": 2023,
            "month": 11,
            "ratio": 1.1344691145470596,
            "velocity": 30.084307016397368,
            "ew_lambda": 768.5549454017755,
            "ns_lambda": 677.457795498138,
            "ew_r2": 0.9593375757496667,
            "ns_r2": 0.9476652954742486,
            "n_ew_pairs": 165621,
            "n_ns_pairs": 173832
          },
          "2023-12": {
            "year": 2023,
            "month": 12,
            "ratio": 0.7980021236720684,
            "velocity": 30.23885263626665,
            "ew_lambda": 703.6109611626794,
            "ns_lambda": 881.7156499846883,
            "ew_r2": 0.9584636405163492,
            "ns_r2": 0.9607057644779381,
            "n_ew_pairs": 197472,
            "n_ns_pairs": 198009
          },
          "2024-01": {
            "year": 2024,
            "month": 1,
            "ratio": 0.5274458439169427,
            "velocity": 30.266810382445737,
            "ew_lambda": 762.4186474716271,
            "ns_lambda": 1445.4918097557058,
            "ew_r2": 0.9700121897871729,
            "ns_r2": 0.8986433587417646,
            "n_ew_pairs": 194246,
            "n_ns_pairs": 200879
          },
          "2024-02": {
            "year": 2024,
            "month": 2,
            "ratio": 1.0119763164930182,
            "velocity": 30.15355743865211,
            "ew_lambda": 946.8619473730131,
            "ns_lambda": 935.656232207432,
            "ew_r2": 0.9452671105762154,
            "ns_r2": 0.8291444964845318,
            "n_ew_pairs": 153543,
            "n_ns_pairs": 170161
          },
          "2024-03": {
            "year": 2024,
            "month": 3,
            "ratio": 1.5271008283339078,
            "velocity": 29.94339266862619,
            "ew_lambda": 1087.899487654919,
            "ns_lambda": 712.3953228693061,
            "ew_r2": 0.9114184397477376,
            "ns_r2": 0.8229392304787926,
            "n_ew_pairs": 161469,
            "n_ns_pairs": 172588
          },
          "2024-04": {
            "year": 2024,
            "month": 4,
            "ratio": 1.563907419156602,
            "velocity": 29.69083901734369,
            "ew_lambda": 1034.8797327455545,
            "ns_lambda": 661.7269795315976,
            "ew_r2": 0.9122410881640072,
            "ns_r2": 0.886710932164376,
            "n_ew_pairs": 160233,
            "n_ns_pairs": 177134
          },
          "2024-05": {
            "year": 2024,
            "month": 5,
            "ratio": 1.261745704758753,
            "velocity": 29.46141635681075,
            "ew_lambda": 743.6402323063564,
            "ns_lambda": 589.3740945593638,
            "ew_r2": 0.9341003177719998,
            "ns_r2": 0.9342909382030693,
            "n_ew_pairs": 208329,
            "n_ns_pairs": 230084
          },
          "2024-06": {
            "year": 2024,
            "month": 6,
            "ratio": 0.984500429011356,
            "velocity": 29.31464369725387,
            "ew_lambda": 665.0181505425318,
            "ns_lambda": 675.4879235658118,
            "ew_r2": 0.9424289356269816,
            "ns_r2": 0.9570797857521668,
            "n_ew_pairs": 230119,
            "n_ns_pairs": 240497
          },
          "2024-07": {
            "year": 2024,
            "month": 7,
            "ratio": 1.0562181076835562,
            "velocity": 29.288598198988613,
            "ew_lambda": 765.1676266846073,
            "ns_lambda": 724.4409285528479,
            "ew_r2": 0.938972805367215,
            "ns_r2": 0.952025017540911,
            "n_ew_pairs": 215763,
            "n_ns_pairs": 225300
          },
          "2024-08": {
            "year": 2024,
            "month": 8,
            "ratio": 1.2200767559454924,
            "velocity": 29.390036833074433,
            "ew_lambda": 816.5516037779481,
            "ns_lambda": 669.2624868057302,
            "ew_r2": 0.957763513162857,
            "ns_r2": 0.9111444584939519,
            "n_ew_pairs": 181858,
            "n_ns_pairs": 203179
          },
          "2024-09": {
            "year": 2024,
            "month": 9,
            "ratio": 1.3446610334745555,
            "velocity": 29.59264342356999,
            "ew_lambda": 696.363484197429,
            "ns_lambda": 517.8728816124395,
            "ew_r2": 0.9658589214398243,
            "ns_r2": 0.9275069292233291,
            "n_ew_pairs": 163372,
            "n_ns_pairs": 180185
          },
          "2024-10": {
            "year": 2024,
            "month": 10,
            "ratio": 1.343827607220809,
            "velocity": 29.843855840371614,
            "ew_lambda": 870.6219344244998,
            "ns_lambda": 647.8672783222892,
            "ew_r2": 0.9408705685834654,
            "ns_r2": 0.92656479068247,
            "n_ew_pairs": 151691,
            "n_ns_pairs": 166234
          },
          "2024-11": {
            "year": 2024,
            "month": 11,
            "ratio": 1.361384051191121,
            "velocity": 30.078502167287997,
            "ew_lambda": 1062.752871889758,
            "ns_lambda": 780.6414883147187,
            "ew_r2": 0.9282939569713007,
            "ns_r2": 0.9167302304429228,
            "n_ew_pairs": 135051,
            "n_ns_pairs": 139551
          },
          "2024-12": {
            "year": 2024,
            "month": 12,
            "ratio": 0.674259652433329,
            "velocity": 30.235708220840905,
            "ew_lambda": 852.4270917364873,
            "ns_lambda": 1264.2415850632196,
            "ew_r2": 0.9250879311697014,
            "ns_r2": 0.8331488121040925,
            "n_ew_pairs": 191153,
            "n_ns_pairs": 197283
          }
        },
        "correlation": {
          "pearson_r": -0.4005664497086539,
          "p_value": 0.0154812795831707,
          "monte_carlo_p": 0.017198280171982803,
          "sigma": 2.4209201006788614,
          "n_months": 36,
          "n_surrogates": 10000
        },
        "seasonal_analysis": {
          "equinox_mean_ratio": 1.3294424249746009,
          "solstice_mean_ratio": 0.9381708597883364,
          "seasonal_contrast": 1.4170578963351521,
          "n_equinox_months": 12,
          "n_solstice_months": 12,
          "modulation_detected": true
        },
        "n_months": 36
      },
      "phase_alignment": {
        "monthly_anisotropy": {
          "2022-01": {
            "year": 2022,
            "month": 1,
            "ratio": 0.9115742347395441,
            "velocity": 30.266752889009627,
            "ew_lambda": 1502.6092169083124,
            "ns_lambda": 1648.367362354904,
            "ew_r2": 0.8651643574543452,
            "ns_r2": 0.8466595892008371,
            "n_ew_pairs": 186899,
            "n_ns_pairs": 192012
          },
          "2022-02": {
            "year": 2022,
            "month": 2,
            "ratio": 1.042289590284473,
            "velocity": 30.152908164805467,
            "ew_lambda": 1652.0303407018191,
            "ns_lambda": 1585.0012857280183,
            "ew_r2": 0.9210560680012703,
            "ns_r2": 0.8346578137825192,
            "n_ew_pairs": 157869,
            "n_ns_pairs": 166222
          },
          "2022-03": {
            "year": 2022,
            "month": 3,
            "ratio": 0.9938479302353928,
            "velocity": 29.941801077621474,
            "ew_lambda": 1552.6023230029678,
            "ns_lambda": 1562.213167395976,
            "ew_r2": 0.9233591201271527,
            "ns_r2": 0.8392347329932858,
            "n_ew_pairs": 191744,
            "n_ns_pairs": 193856
          },
          "2022-04": {
            "year": 2022,
            "month": 4,
            "ratio": 1.0031068375553083,
            "velocity": 29.688492835763494,
            "ew_lambda": 1719.7316788194846,
            "ns_lambda": 1714.4053000482752,
            "ew_r2": 0.9159913674963424,
            "ns_r2": 0.8871868384095476,
            "n_ew_pairs": 179335,
            "n_ns_pairs": 187021
          },
          "2022-05": {
            "year": 2022,
            "month": 5,
            "ratio": 1.0600995489237455,
            "velocity": 29.459051604240003,
            "ew_lambda": 1807.4906369345479,
            "ns_lambda": 1705.0197208079026,
            "ew_r2": 0.913303524087963,
            "ns_r2": 0.8686714981643261,
            "n_ew_pairs": 185511,
            "n_ns_pairs": 207682
          },
          "2022-06": {
            "year": 2022,
            "month": 6,
            "ratio": 0.9648540567819534,
            "velocity": 29.31332052527508,
            "ew_lambda": 1712.8850242318981,
            "ns_lambda": 1775.2788747604259,
            "ew_r2": 0.8957217141974313,
            "ns_r2": 0.8997815453128477,
            "n_ew_pairs": 258765,
            "n_ns_pairs": 262049
          },
          "2022-07": {
            "year": 2022,
            "month": 7,
            "ratio": 1.049090784691398,
            "velocity": 29.289309356866724,
            "ew_lambda": 1788.7035208234545,
            "ns_lambda": 1705.003558247461,
            "ew_r2": 0.9006883475589669,
            "ns_r2": 0.8343774110935027,
            "n_ew_pairs": 206095,
            "n_ns_pairs": 211006
          },
          "2022-08": {
            "year": 2022,
            "month": 8,
            "ratio": 1.010253100408311,
            "velocity": 29.393280721284196,
            "ew_lambda": 1713.6188905668769,
            "ns_lambda": 1696.2273017269517,
            "ew_r2": 0.8600686185855779,
            "ns_r2": 0.7913255364113014,
            "n_ew_pairs": 206793,
            "n_ns_pairs": 213789
          },
          "2022-09": {
            "year": 2022,
            "month": 9,
            "ratio": 0.9258523282209277,
            "velocity": 29.598116680279198,
            "ew_lambda": 1633.3726116283526,
            "ns_lambda": 1764.1826475362018,
            "ew_r2": 0.8518812147717445,
            "ns_r2": 0.867910348021526,
            "n_ew_pairs": 196629,
            "n_ns_pairs": 204525
          },
          "2022-10": {
            "year": 2022,
            "month": 10,
            "ratio": 0.9370636314230568,
            "velocity": 29.85039166885911,
            "ew_lambda": 1714.421060896986,
            "ns_lambda": 1829.567388388991,
            "ew_r2": 0.9416532530173631,
            "ns_r2": 0.9284565918286802,
            "n_ew_pairs": 176817,
            "n_ns_pairs": 193359
          },
          "2022-11": {
            "year": 2022,
            "month": 11,
            "ratio": 1.092903541305826,
            "velocity": 30.084307016397368,
            "ew_lambda": 1631.1848727155343,
            "ns_lambda": 1492.5240984822483,
            "ew_r2": 0.9006099923282762,
            "ns_r2": 0.8958817460711092,
            "n_ew_pairs": 176894,
            "n_ns_pairs": 185830
          },
          "2022-12": {
            "year": 2022,
            "month": 12,
            "ratio": 0.834830138263652,
            "velocity": 30.23885263626665,
            "ew_lambda": 1379.07212414522,
            "ns_lambda": 1651.9194276017956,
            "ew_r2": 0.8879992673709023,
            "ns_r2": 0.8687441917517307,
            "n_ew_pairs": 180852,
            "n_ns_pairs": 185246
          },
          "2023-01": {
            "year": 2023,
            "month": 1,
            "ratio": 0.7447750788369545,
            "velocity": 30.266752889009627,
            "ew_lambda": 1445.8035320114464,
            "ns_lambda": 1941.2619636376965,
            "ew_r2": 0.9542111505182479,
            "ns_r2": 0.9420878469551096,
            "n_ew_pairs": 174368,
            "n_ns_pairs": 177259
          },
          "2023-02": {
            "year": 2023,
            "month": 2,
            "ratio": 0.7338910158867018,
            "velocity": 30.152908164805467,
            "ew_lambda": 1311.7096051847864,
            "ns_lambda": 1787.3356898911654,
            "ew_r2": 0.9253847009836007,
            "ns_r2": 0.9393809666786965,
            "n_ew_pairs": 155946,
            "n_ns_pairs": 163652
          },
          "2023-03": {
            "year": 2023,
            "month": 3,
            "ratio": 0.9853433995756136,
            "velocity": 29.941801077621474,
            "ew_lambda": 1657.8090447701168,
            "ns_lambda": 1682.468310524162,
            "ew_r2": 0.9426037229963898,
            "ns_r2": 0.8809447780156809,
            "n_ew_pairs": 149067,
            "n_ns_pairs": 167098
          },
          "2023-04": {
            "year": 2023,
            "month": 4,
            "ratio": 0.8865569329105109,
            "velocity": 29.688492835763494,
            "ew_lambda": 1700.3242057710538,
            "ns_lambda": 1917.8962372884457,
            "ew_r2": 0.8985250688955959,
            "ns_r2": 0.8750171191902676,
            "n_ew_pairs": 160574,
            "n_ns_pairs": 174909
          },
          "2023-05": {
            "year": 2023,
            "month": 5,
            "ratio": 0.846006380911065,
            "velocity": 29.459051604240003,
            "ew_lambda": 1745.7520932322714,
            "ns_lambda": 2063.5211892282296,
            "ew_r2": 0.8879488211884029,
            "ns_r2": 0.9115553196174393,
            "n_ew_pairs": 194088,
            "n_ns_pairs": 195004
          },
          "2023-06": {
            "year": 2023,
            "month": 6,
            "ratio": 0.7971324089950586,
            "velocity": 29.31332052527508,
            "ew_lambda": 1547.241506901438,
            "ns_lambda": 1941.009410032693,
            "ew_r2": 0.8818501486270605,
            "ns_r2": 0.8927455527403771,
            "n_ew_pairs": 205395,
            "n_ns_pairs": 209179
          },
          "2023-07": {
            "year": 2023,
            "month": 7,
            "ratio": 0.9396239340066372,
            "velocity": 29.289309356866724,
            "ew_lambda": 1632.744304026754,
            "ns_lambda": 1737.6572104380014,
            "ew_r2": 0.8768120140386721,
            "ns_r2": 0.8439433444859724,
            "n_ew_pairs": 213008,
            "n_ns_pairs": 214576
          },
          "2023-08": {
            "year": 2023,
            "month": 8,
            "ratio": 1.1008914763376045,
            "velocity": 29.393280721284196,
            "ew_lambda": 1620.1821684651202,
            "ns_lambda": 1471.7001659918997,
            "ew_r2": 0.8863893548855175,
            "ns_r2": 0.8063662458045547,
            "n_ew_pairs": 198275,
            "n_ns_pairs": 203089
          },
          "2023-09": {
            "year": 2023,
            "month": 9,
            "ratio": 0.9599610423149724,
            "velocity": 29.598116680279198,
            "ew_lambda": 1529.9384572142574,
            "ns_lambda": 1593.7505687988846,
            "ew_r2": 0.9211686570593884,
            "ns_r2": 0.9013349062396951,
            "n_ew_pairs": 177003,
            "n_ns_pairs": 191794
          },
          "2023-10": {
            "year": 2023,
            "month": 10,
            "ratio": 0.8588522986722651,
            "velocity": 29.85039166885911,
            "ew_lambda": 1557.0514553643402,
            "ns_lambda": 1812.9443884256348,
            "ew_r2": 0.92799279948337,
            "ns_r2": 0.9311157734551491,
            "n_ew_pairs": 167537,
            "n_ns_pairs": 185897
          },
          "2023-11": {
            "year": 2023,
            "month": 11,
            "ratio": 0.9752702412368869,
            "velocity": 30.084307016397368,
            "ew_lambda": 1688.5423232724052,
            "ns_lambda": 1731.358398807402,
            "ew_r2": 0.9161225056312048,
            "ns_r2": 0.8845573880937674,
            "n_ew_pairs": 165621,
            "n_ns_pairs": 173832
          },
          "2023-12": {
            "year": 2023,
            "month": 12,
            "ratio": 0.7326862600939642,
            "velocity": 30.23885263626665,
            "ew_lambda": 1533.0858195126975,
            "ns_lambda": 2092.417864252136,
            "ew_r2": 0.903654503371369,
            "ns_r2": 0.9104275276008259,
            "n_ew_pairs": 197472,
            "n_ns_pairs": 198009
          },
          "2024-01": {
            "year": 2024,
            "month": 1,
            "ratio": 0.660030168849989,
            "velocity": 30.266810382445737,
            "ew_lambda": 1293.0462528016778,
            "ns_lambda": 1959.071439195926,
            "ew_r2": 0.8895632712672826,
            "ns_r2": 0.8880689085505248,
            "n_ew_pairs": 194246,
            "n_ns_pairs": 200879
          },
          "2024-02": {
            "year": 2024,
            "month": 2,
            "ratio": 0.7054667269526737,
            "velocity": 30.15355743865211,
            "ew_lambda": 1511.2856373450377,
            "ns_lambda": 2142.249350119134,
            "ew_r2": 0.9332612945894204,
            "ns_r2": 0.9536145132811606,
            "n_ew_pairs": 153543,
            "n_ns_pairs": 170161
          },
          "2024-03": {
            "year": 2024,
            "month": 3,
            "ratio": 0.8278922693121245,
            "velocity": 29.94339266862619,
            "ew_lambda": 2047.5498639242005,
            "ns_lambda": 2473.2080970214397,
            "ew_r2": 0.9454626406791057,
            "ns_r2": 0.9583355801440118,
            "n_ew_pairs": 161469,
            "n_ns_pairs": 172588
          },
          "2024-04": {
            "year": 2024,
            "month": 4,
            "ratio": 0.8446400871123418,
            "velocity": 29.69083901734369,
            "ew_lambda": 2095.452297018946,
            "ns_lambda": 2480.88189157927,
            "ew_r2": 0.9516724261205676,
            "ns_r2": 0.956904475215583,
            "n_ew_pairs": 160233,
            "n_ns_pairs": 177134
          },
          "2024-05": {
            "year": 2024,
            "month": 5,
            "ratio": 0.8791264304453995,
            "velocity": 29.46141635681075,
            "ew_lambda": 1765.2386258790496,
            "ns_lambda": 2007.946257496446,
            "ew_r2": 0.9424832383728526,
            "ns_r2": 0.9331498780504097,
            "n_ew_pairs": 208329,
            "n_ns_pairs": 230084
          },
          "2024-06": {
            "year": 2024,
            "month": 6,
            "ratio": 0.8863109306561651,
            "velocity": 29.31464369725387,
            "ew_lambda": 1795.3981131014807,
            "ns_lambda": 2025.6978121349453,
            "ew_r2": 0.9291488473568416,
            "ns_r2": 0.8952818324718519,
            "n_ew_pairs": 230119,
            "n_ns_pairs": 240497
          },
          "2024-07": {
            "year": 2024,
            "month": 7,
            "ratio": 0.9452234447192548,
            "velocity": 29.288598198988613,
            "ew_lambda": 1794.6158311847305,
            "ns_lambda": 1898.6154450683962,
            "ew_r2": 0.9665522927252782,
            "ns_r2": 0.851534495232821,
            "n_ew_pairs": 215763,
            "n_ns_pairs": 225300
          },
          "2024-08": {
            "year": 2024,
            "month": 8,
            "ratio": 1.1691760997367202,
            "velocity": 29.390036833074433,
            "ew_lambda": 2188.403535027537,
            "ns_lambda": 1871.7484350906,
            "ew_r2": 0.9757536150713376,
            "ns_r2": 0.9190676925466625,
            "n_ew_pairs": 181858,
            "n_ns_pairs": 203179
          },
          "2024-09": {
            "year": 2024,
            "month": 9,
            "ratio": 1.2174178709277512,
            "velocity": 29.59264342356999,
            "ew_lambda": 2038.234535368707,
            "ns_lambda": 1674.227546713636,
            "ew_r2": 0.9642398576057102,
            "ns_r2": 0.9651256831012328,
            "n_ew_pairs": 163372,
            "n_ns_pairs": 180185
          },
          "2024-10": {
            "year": 2024,
            "month": 10,
            "ratio": 1.078527286101655,
            "velocity": 29.843855840371614,
            "ew_lambda": 1681.9669726175493,
            "ns_lambda": 1559.5034027345118,
            "ew_r2": 0.9360320748027189,
            "ns_r2": 0.9324448584927312,
            "n_ew_pairs": 151691,
            "n_ns_pairs": 166234
          },
          "2024-11": {
            "year": 2024,
            "month": 11,
            "ratio": 1.0957095891290407,
            "velocity": 30.078502167287997,
            "ew_lambda": 1798.2954035949358,
            "ns_lambda": 1641.215356182442,
            "ew_r2": 0.9446485812359846,
            "ns_r2": 0.9142274603900968,
            "n_ew_pairs": 135051,
            "n_ns_pairs": 139551
          },
          "2024-12": {
            "year": 2024,
            "month": 12,
            "ratio": 0.8508068922646863,
            "velocity": 30.235708220840905,
            "ew_lambda": 1766.3674306211435,
            "ns_lambda": 2076.10851143837,
            "ew_r2": 0.9491173692624343,
            "ns_r2": 0.9006118519807409,
            "n_ew_pairs": 191153,
            "n_ns_pairs": 197283
          }
        },
        "correlation": {
          "pearson_r": -0.3907011821801486,
          "p_value": 0.018473866585306458,
          "monte_carlo_p": 0.021397860213978603,
          "sigma": 2.3559809193826267,
          "n_months": 36,
          "n_surrogates": 10000
        },
        "seasonal_analysis": {
          "equinox_mean_ratio": 0.9599218261968266,
          "solstice_mean_ratio": 0.8597448610749381,
          "seasonal_contrast": 1.1165194113479637,
          "n_equinox_months": 12,
          "n_solstice_months": 12,
          "modulation_detected": false
        },
        "n_months": 36
      }
    },
    "pos_jitter": {
      "msc": {
        "monthly_anisotropy": {
          "2022-01": {
            "year": 2022,
            "month": 1,
            "ratio": 1.0741297882210383,
            "velocity": 30.266752889009627,
            "ew_lambda": 673.2361046693841,
            "ns_lambda": 626.7735166198026,
            "ew_r2": 0.9626260530336224,
            "ns_r2": 0.9876448112990817,
            "n_ew_pairs": 186899,
            "n_ns_pairs": 192012
          },
          "2022-02": {
            "year": 2022,
            "month": 2,
            "ratio": 0.9360041636048,
            "velocity": 30.152908164805467,
            "ew_lambda": 683.5709228681958,
            "ns_lambda": 730.3075664060971,
            "ew_r2": 0.9661901495345127,
            "ns_r2": 0.9885986483042385,
            "n_ew_pairs": 157869,
            "n_ns_pairs": 166222
          },
          "2022-03": {
            "year": 2022,
            "month": 3,
            "ratio": 1.1553447865488653,
            "velocity": 29.941801077621474,
            "ew_lambda": 822.8446197113493,
            "ns_lambda": 712.2069786364567,
            "ew_r2": 0.9648470542617631,
            "ns_r2": 0.9426914855083428,
            "n_ew_pairs": 191744,
            "n_ns_pairs": 193856
          },
          "2022-04": {
            "year": 2022,
            "month": 4,
            "ratio": 1.2948788408450371,
            "velocity": 29.688492835763494,
            "ew_lambda": 898.8091211814847,
            "ns_lambda": 694.1260393095329,
            "ew_r2": 0.9624827255148414,
            "ns_r2": 0.9453879087528654,
            "n_ew_pairs": 179335,
            "n_ns_pairs": 187021
          },
          "2022-05": {
            "year": 2022,
            "month": 5,
            "ratio": 1.3501767646828384,
            "velocity": 29.459051604240003,
            "ew_lambda": 951.8924173869434,
            "ns_lambda": 705.0131821891829,
            "ew_r2": 0.9679274134816256,
            "ns_r2": 0.9477030389591681,
            "n_ew_pairs": 185511,
            "n_ns_pairs": 207682
          },
          "2022-06": {
            "year": 2022,
            "month": 6,
            "ratio": 1.1732128883209902,
            "velocity": 29.31332052527508,
            "ew_lambda": 1046.696643197878,
            "ns_lambda": 892.1625849983866,
            "ew_r2": 0.975034884425452,
            "ns_r2": 0.9658040330290041,
            "n_ew_pairs": 258765,
            "n_ns_pairs": 262049
          },
          "2022-07": {
            "year": 2022,
            "month": 7,
            "ratio": 1.2059913150585309,
            "velocity": 29.289309356866724,
            "ew_lambda": 1216.1370338152535,
            "ns_lambda": 1008.4127627040417,
            "ew_r2": 0.9646826634412877,
            "ns_r2": 0.9679789576081804,
            "n_ew_pairs": 206095,
            "n_ns_pairs": 211006
          },
          "2022-08": {
            "year": 2022,
            "month": 8,
            "ratio": 1.241777075712543,
            "velocity": 29.393280721284196,
            "ew_lambda": 1111.36685523664,
            "ns_lambda": 894.980972811829,
            "ew_r2": 0.9671142452214214,
            "ns_r2": 0.9693722517253472,
            "n_ew_pairs": 206793,
            "n_ns_pairs": 213789
          },
          "2022-09": {
            "year": 2022,
            "month": 9,
            "ratio": 1.249200003001179,
            "velocity": 29.598116680279198,
            "ew_lambda": 888.9456497632438,
            "ns_lambda": 711.6119497498951,
            "ew_r2": 0.9747833742186776,
            "ns_r2": 0.9781557722956723,
            "n_ew_pairs": 196629,
            "n_ns_pairs": 204525
          },
          "2022-10": {
            "year": 2022,
            "month": 10,
            "ratio": 1.3751554641324704,
            "velocity": 29.85039166885911,
            "ew_lambda": 920.7148871979124,
            "ns_lambda": 669.5351261820815,
            "ew_r2": 0.9733552033088798,
            "ns_r2": 0.9737127005942341,
            "n_ew_pairs": 176817,
            "n_ns_pairs": 193359
          },
          "2022-11": {
            "year": 2022,
            "month": 11,
            "ratio": 1.160897677668645,
            "velocity": 30.084307016397368,
            "ew_lambda": 878.8371420345384,
            "ns_lambda": 757.0323887626768,
            "ew_r2": 0.9806298526071642,
            "ns_r2": 0.9847212595893845,
            "n_ew_pairs": 176894,
            "n_ns_pairs": 185830
          },
          "2022-12": {
            "year": 2022,
            "month": 12,
            "ratio": 0.8179907769826233,
            "velocity": 30.23885263626665,
            "ew_lambda": 832.1541143084186,
            "ns_lambda": 1017.3147885334851,
            "ew_r2": 0.9749582177884701,
            "ns_r2": 0.979660325360336,
            "n_ew_pairs": 180852,
            "n_ns_pairs": 185246
          },
          "2023-01": {
            "year": 2023,
            "month": 1,
            "ratio": 0.7538282192806937,
            "velocity": 30.266752889009627,
            "ew_lambda": 894.9408904056378,
            "ns_lambda": 1187.1947315259629,
            "ew_r2": 0.9749395854920592,
            "ns_r2": 0.9693393065998569,
            "n_ew_pairs": 174368,
            "n_ns_pairs": 177259
          },
          "2023-02": {
            "year": 2023,
            "month": 2,
            "ratio": 1.1495374794783726,
            "velocity": 30.152908164805467,
            "ew_lambda": 835.0551994060058,
            "ns_lambda": 726.4271190052282,
            "ew_r2": 0.9623175979628762,
            "ns_r2": 0.9762750898772665,
            "n_ew_pairs": 155946,
            "n_ns_pairs": 163652
          },
          "2023-03": {
            "year": 2023,
            "month": 3,
            "ratio": 1.1697682562307157,
            "velocity": 29.941801077621474,
            "ew_lambda": 724.9909731184306,
            "ns_lambda": 619.7731638354865,
            "ew_r2": 0.9598821543397817,
            "ns_r2": 0.9705800458372611,
            "n_ew_pairs": 149067,
            "n_ns_pairs": 167098
          },
          "2023-04": {
            "year": 2023,
            "month": 4,
            "ratio": 1.2677828796139157,
            "velocity": 29.688492835763494,
            "ew_lambda": 791.6369235504379,
            "ns_lambda": 624.4262612155791,
            "ew_r2": 0.9702052231909563,
            "ns_r2": 0.9647510722510475,
            "n_ew_pairs": 160574,
            "n_ns_pairs": 174909
          },
          "2023-05": {
            "year": 2023,
            "month": 5,
            "ratio": 1.2629420206728088,
            "velocity": 29.459051604240003,
            "ew_lambda": 1054.0504326837922,
            "ns_lambda": 834.5992257999828,
            "ew_r2": 0.9698765755458421,
            "ns_r2": 0.9654985086500442,
            "n_ew_pairs": 194088,
            "n_ns_pairs": 195004
          },
          "2023-06": {
            "year": 2023,
            "month": 6,
            "ratio": 1.0852745019010652,
            "velocity": 29.31332052527508,
            "ew_lambda": 1053.3960838687265,
            "ns_lambda": 970.6264009921014,
            "ew_r2": 0.9676552066920802,
            "ns_r2": 0.9708473992774352,
            "n_ew_pairs": 205395,
            "n_ns_pairs": 209179
          },
          "2023-07": {
            "year": 2023,
            "month": 7,
            "ratio": 1.3403989556876035,
            "velocity": 29.289309356866724,
            "ew_lambda": 1819.5047350791135,
            "ns_lambda": 1357.4352078972909,
            "ew_r2": 0.9672810238785203,
            "ns_r2": 0.9715656403782379,
            "n_ew_pairs": 213008,
            "n_ns_pairs": 214576
          },
          "2023-08": {
            "year": 2023,
            "month": 8,
            "ratio": 1.5524880965850167,
            "velocity": 29.393280721284196,
            "ew_lambda": 1307.4120856001787,
            "ns_lambda": 842.1398453721301,
            "ew_r2": 0.9716199198150148,
            "ns_r2": 0.9607256581770631,
            "n_ew_pairs": 198275,
            "n_ns_pairs": 203089
          },
          "2023-09": {
            "year": 2023,
            "month": 9,
            "ratio": 1.1836672037581717,
            "velocity": 29.598116680279198,
            "ew_lambda": 1044.368385399327,
            "ns_lambda": 882.3158925781102,
            "ew_r2": 0.9814968868162246,
            "ns_r2": 0.9525342127135183,
            "n_ew_pairs": 177003,
            "n_ns_pairs": 191794
          },
          "2023-10": {
            "year": 2023,
            "month": 10,
            "ratio": 1.3110447973346344,
            "velocity": 29.85039166885911,
            "ew_lambda": 1034.8377804840677,
            "ns_lambda": 789.3229755290605,
            "ew_r2": 0.9824578709949978,
            "ns_r2": 0.9701043284492729,
            "n_ew_pairs": 167537,
            "n_ns_pairs": 185897
          },
          "2023-11": {
            "year": 2023,
            "month": 11,
            "ratio": 1.2310984816085153,
            "velocity": 30.084307016397368,
            "ew_lambda": 1012.2458191466559,
            "ns_lambda": 822.2297681856343,
            "ew_r2": 0.9813341599255558,
            "ns_r2": 0.9754128248430034,
            "n_ew_pairs": 165621,
            "n_ns_pairs": 173832
          },
          "2023-12": {
            "year": 2023,
            "month": 12,
            "ratio": 0.9964865894354282,
            "velocity": 30.23885263626665,
            "ew_lambda": 919.3912403396878,
            "ns_lambda": 922.6328282657373,
            "ew_r2": 0.9772966307507968,
            "ns_r2": 0.9773251932297958,
            "n_ew_pairs": 197472,
            "n_ns_pairs": 198009
          },
          "2024-01": {
            "year": 2024,
            "month": 1,
            "ratio": 0.6962263001089992,
            "velocity": 30.266810382445737,
            "ew_lambda": 901.183686141892,
            "ns_lambda": 1294.3832860103178,
            "ew_r2": 0.981864977866405,
            "ns_r2": 0.9289262015118698,
            "n_ew_pairs": 194246,
            "n_ns_pairs": 200879
          },
          "2024-02": {
            "year": 2024,
            "month": 2,
            "ratio": 0.9520101589855193,
            "velocity": 30.15355743865211,
            "ew_lambda": 1135.9277618978986,
            "ns_lambda": 1193.1886978058778,
            "ew_r2": 0.959295071892888,
            "ns_r2": 0.9038086040163776,
            "n_ew_pairs": 153543,
            "n_ns_pairs": 170161
          },
          "2024-03": {
            "year": 2024,
            "month": 3,
            "ratio": 1.3605584841625415,
            "velocity": 29.94339266862619,
            "ew_lambda": 1028.3047842593542,
            "ns_lambda": 755.7960912590258,
            "ew_r2": 0.946486523961038,
            "ns_r2": 0.8783515052457614,
            "n_ew_pairs": 161469,
            "n_ns_pairs": 172588
          },
          "2024-04": {
            "year": 2024,
            "month": 4,
            "ratio": 1.8007550991372248,
            "velocity": 29.69083901734369,
            "ew_lambda": 1210.043437117816,
            "ns_lambda": 671.9644651832836,
            "ew_r2": 0.9363025344222938,
            "ns_r2": 0.9098023026524337,
            "n_ew_pairs": 160233,
            "n_ns_pairs": 177134
          },
          "2024-05": {
            "year": 2024,
            "month": 5,
            "ratio": 1.2577010588140307,
            "velocity": 29.46141635681075,
            "ew_lambda": 949.1784049321299,
            "ns_lambda": 754.6931747256162,
            "ew_r2": 0.958111541639745,
            "ns_r2": 0.9552391579285469,
            "n_ew_pairs": 208329,
            "n_ns_pairs": 230084
          },
          "2024-06": {
            "year": 2024,
            "month": 6,
            "ratio": 0.81072090639349,
            "velocity": 29.31464369725387,
            "ew_lambda": 789.954150343144,
            "ns_lambda": 974.3848272733862,
            "ew_r2": 0.9459470752076894,
            "ns_r2": 0.9579279767492973,
            "n_ew_pairs": 230119,
            "n_ns_pairs": 240497
          },
          "2024-07": {
            "year": 2024,
            "month": 7,
            "ratio": 1.1716675367675495,
            "velocity": 29.288598198988613,
            "ew_lambda": 749.2745001591143,
            "ns_lambda": 639.4941198304831,
            "ew_r2": 0.9668288323483225,
            "ns_r2": 0.9427976627834452,
            "n_ew_pairs": 215763,
            "n_ns_pairs": 225300
          },
          "2024-08": {
            "year": 2024,
            "month": 8,
            "ratio": 1.4234695670230777,
            "velocity": 29.390036833074433,
            "ew_lambda": 909.8044898252167,
            "ns_lambda": 639.1457259798703,
            "ew_r2": 0.9608362399666674,
            "ns_r2": 0.9187651038849646,
            "n_ew_pairs": 181858,
            "n_ns_pairs": 203179
          },
          "2024-09": {
            "year": 2024,
            "month": 9,
            "ratio": 1.4883793444638873,
            "velocity": 29.59264342356999,
            "ew_lambda": 810.3100870543965,
            "ns_lambda": 544.4244372702373,
            "ew_r2": 0.9714652718093385,
            "ns_r2": 0.9299834605486289,
            "n_ew_pairs": 163372,
            "n_ns_pairs": 180185
          },
          "2024-10": {
            "year": 2024,
            "month": 10,
            "ratio": 1.5673990766777477,
            "velocity": 29.843855840371614,
            "ew_lambda": 1120.5347360805488,
            "ns_lambda": 714.9007248719512,
            "ew_r2": 0.9269911097300887,
            "ns_r2": 0.9115340716560696,
            "n_ew_pairs": 151691,
            "n_ns_pairs": 166234
          },
          "2024-11": {
            "year": 2024,
            "month": 11,
            "ratio": 1.5097505903945327,
            "velocity": 30.078502167287997,
            "ew_lambda": 1885.7255057556308,
            "ns_lambda": 1249.031143125996,
            "ew_r2": 0.947000789474551,
            "ns_r2": 0.948212427093254,
            "n_ew_pairs": 135051,
            "n_ns_pairs": 139551
          },
          "2024-12": {
            "year": 2024,
            "month": 12,
            "ratio": 0.6908468727584397,
            "velocity": 30.235708220840905,
            "ew_lambda": 1029.8094026964386,
            "ns_lambda": 1490.647845859932,
            "ew_r2": 0.9566825123344933,
            "ns_r2": 0.9164108582017103,
            "n_ew_pairs": 191153,
            "n_ns_pairs": 197283
          }
        },
        "correlation": {
          "pearson_r": -0.43519470663247717,
          "p_value": 0.007985439001888885,
          "monte_carlo_p": 0.0071992800719928,
          "sigma": 2.6526848499260844,
          "n_months": 36,
          "n_surrogates": 10000
        },
        "seasonal_analysis": {
          "equinox_mean_ratio": 1.3519945196588659,
          "solstice_mean_ratio": 0.9847312209097043,
          "seasonal_contrast": 1.372957910697581,
          "n_equinox_months": 12,
          "n_solstice_months": 12,
          "modulation_detected": true
        },
        "n_months": 36
      },
      "phase_alignment": {
        "monthly_anisotropy": {
          "2022-01": {
            "year": 2022,
            "month": 1,
            "ratio": 1.2626382421889557,
            "velocity": 30.266752889009627,
            "ew_lambda": 2121.824682450392,
            "ns_lambda": 1680.4692045220486,
            "ew_r2": 0.9630600278916981,
            "ns_r2": 0.9429301182700222,
            "n_ew_pairs": 186899,
            "n_ns_pairs": 192012
          },
          "2022-02": {
            "year": 2022,
            "month": 2,
            "ratio": 0.5621619559671824,
            "velocity": 30.152908164805467,
            "ew_lambda": 1367.2517877029338,
            "ns_lambda": 2432.1314759740703,
            "ew_r2": 0.9153764117691905,
            "ns_r2": 0.957683834749832,
            "n_ew_pairs": 157869,
            "n_ns_pairs": 166222
          },
          "2022-03": {
            "year": 2022,
            "month": 3,
            "ratio": 0.951951883080835,
            "velocity": 29.941801077621474,
            "ew_lambda": 1771.9082931317475,
            "ns_lambda": 1861.3422848613516,
            "ew_r2": 0.9322306140736721,
            "ns_r2": 0.9586682359834222,
            "n_ew_pairs": 191744,
            "n_ns_pairs": 193856
          },
          "2022-04": {
            "year": 2022,
            "month": 4,
            "ratio": 1.0693042495199943,
            "velocity": 29.688492835763494,
            "ew_lambda": 1758.6600021542786,
            "ns_lambda": 1644.6769036443397,
            "ew_r2": 0.9349577980233033,
            "ns_r2": 0.9477554035031469,
            "n_ew_pairs": 179335,
            "n_ns_pairs": 187021
          },
          "2022-05": {
            "year": 2022,
            "month": 5,
            "ratio": 1.0676457436431712,
            "velocity": 29.459051604240003,
            "ew_lambda": 2090.0150199014965,
            "ns_lambda": 1957.5922372618213,
            "ew_r2": 0.9315495559876993,
            "ns_r2": 0.9717084655153664,
            "n_ew_pairs": 185511,
            "n_ns_pairs": 207682
          },
          "2022-06": {
            "year": 2022,
            "month": 6,
            "ratio": 1.2806835430545227,
            "velocity": 29.31332052527508,
            "ew_lambda": 2552.922739816119,
            "ns_lambda": 1993.4063755728553,
            "ew_r2": 0.957063369379923,
            "ns_r2": 0.9645999521586153,
            "n_ew_pairs": 258765,
            "n_ns_pairs": 262049
          },
          "2022-07": {
            "year": 2022,
            "month": 7,
            "ratio": 1.3367945880185237,
            "velocity": 29.289309356866724,
            "ew_lambda": 3092.574304680228,
            "ns_lambda": 2313.4252131168673,
            "ew_r2": 0.9693898874197144,
            "ns_r2": 0.9545715610967488,
            "n_ew_pairs": 206095,
            "n_ns_pairs": 211006
          },
          "2022-08": {
            "year": 2022,
            "month": 8,
            "ratio": 1.5072548191356785,
            "velocity": 29.393280721284196,
            "ew_lambda": 2867.1392868437956,
            "ns_lambda": 1902.2259875658785,
            "ew_r2": 0.9737069958019522,
            "ns_r2": 0.9390158600388762,
            "n_ew_pairs": 206793,
            "n_ns_pairs": 213789
          },
          "2022-09": {
            "year": 2022,
            "month": 9,
            "ratio": 1.378054468489997,
            "velocity": 29.598116680279198,
            "ew_lambda": 2391.710163708794,
            "ns_lambda": 1735.5701232401286,
            "ew_r2": 0.9732383199333432,
            "ns_r2": 0.9414533495143758,
            "n_ew_pairs": 196629,
            "n_ns_pairs": 204525
          },
          "2022-10": {
            "year": 2022,
            "month": 10,
            "ratio": 1.1300981091113167,
            "velocity": 29.85039166885911,
            "ew_lambda": 2199.038907128251,
            "ns_lambda": 1945.8831842993923,
            "ew_r2": 0.9597000519926299,
            "ns_r2": 0.9702714390970444,
            "n_ew_pairs": 176817,
            "n_ns_pairs": 193359
          },
          "2022-11": {
            "year": 2022,
            "month": 11,
            "ratio": 0.8776852167700636,
            "velocity": 30.084307016397368,
            "ew_lambda": 1730.4790081398992,
            "ns_lambda": 1971.6396893503231,
            "ew_r2": 0.9028263084354216,
            "ns_r2": 0.9558517780193369,
            "n_ew_pairs": 176894,
            "n_ns_pairs": 185830
          },
          "2022-12": {
            "year": 2022,
            "month": 12,
            "ratio": 0.7567856154911192,
            "velocity": 30.23885263626665,
            "ew_lambda": 1579.374409017879,
            "ns_lambda": 2086.9508836963523,
            "ew_r2": 0.8559861776150436,
            "ns_r2": 0.9265297230715307,
            "n_ew_pairs": 180852,
            "n_ns_pairs": 185246
          },
          "2023-01": {
            "year": 2023,
            "month": 1,
            "ratio": 0.8883534202660055,
            "velocity": 30.266752889009627,
            "ew_lambda": 1802.5527312465751,
            "ns_lambda": 2029.0941534359433,
            "ew_r2": 0.8682717371480729,
            "ns_r2": 0.908474378002036,
            "n_ew_pairs": 174368,
            "n_ns_pairs": 177259
          },
          "2023-02": {
            "year": 2023,
            "month": 2,
            "ratio": 1.0209177565809537,
            "velocity": 30.152908164805467,
            "ew_lambda": 1970.9595775630116,
            "ns_lambda": 1930.5762534327362,
            "ew_r2": 0.9462166272622305,
            "ns_r2": 0.9656136707501318,
            "n_ew_pairs": 155946,
            "n_ns_pairs": 163652
          },
          "2023-03": {
            "year": 2023,
            "month": 3,
            "ratio": 1.0191821268231707,
            "velocity": 29.941801077621474,
            "ew_lambda": 2175.1810060427406,
            "ns_lambda": 2134.241710873465,
            "ew_r2": 0.9623104864642933,
            "ns_r2": 0.9690075310570603,
            "n_ew_pairs": 149067,
            "n_ns_pairs": 167098
          },
          "2023-04": {
            "year": 2023,
            "month": 4,
            "ratio": 1.2461463082892568,
            "velocity": 29.688492835763494,
            "ew_lambda": 2495.750256393103,
            "ns_lambda": 2002.7746660176174,
            "ew_r2": 0.9624702125084581,
            "ns_r2": 0.9513328242681307,
            "n_ew_pairs": 160574,
            "n_ns_pairs": 174909
          },
          "2023-05": {
            "year": 2023,
            "month": 5,
            "ratio": 1.2467163264506431,
            "velocity": 29.459051604240003,
            "ew_lambda": 2354.804648648458,
            "ns_lambda": 1888.8054954349582,
            "ew_r2": 0.9496272590113657,
            "ns_r2": 0.9449028168741922,
            "n_ew_pairs": 194088,
            "n_ns_pairs": 195004
          },
          "2023-06": {
            "year": 2023,
            "month": 6,
            "ratio": 1.0777073682023628,
            "velocity": 29.31332052527508,
            "ew_lambda": 2466.415534125057,
            "ns_lambda": 2288.576293432128,
            "ew_r2": 0.9632591206339524,
            "ns_r2": 0.9735961703450157,
            "n_ew_pairs": 205395,
            "n_ns_pairs": 209179
          },
          "2023-07": {
            "year": 2023,
            "month": 7,
            "ratio": 1.101719723495064,
            "velocity": 29.289309356866724,
            "ew_lambda": 2743.4761748586443,
            "ns_lambda": 2490.176145848891,
            "ew_r2": 0.9752213454100123,
            "ns_r2": 0.9766191288728364,
            "n_ew_pairs": 213008,
            "n_ns_pairs": 214576
          },
          "2023-08": {
            "year": 2023,
            "month": 8,
            "ratio": 1.591765115378629,
            "velocity": 29.393280721284196,
            "ew_lambda": 3198.0985257818625,
            "ns_lambda": 2009.1522894199998,
            "ew_r2": 0.9809007181560822,
            "ns_r2": 0.9648496930384037,
            "n_ew_pairs": 198275,
            "n_ns_pairs": 203089
          },
          "2023-09": {
            "year": 2023,
            "month": 9,
            "ratio": 1.2275319781519036,
            "velocity": 29.598116680279198,
            "ew_lambda": 1947.8426168096587,
            "ns_lambda": 1586.795824042165,
            "ew_r2": 0.9454002861407622,
            "ns_r2": 0.9329878906020608,
            "n_ew_pairs": 177003,
            "n_ns_pairs": 191794
          },
          "2023-10": {
            "year": 2023,
            "month": 10,
            "ratio": 1.2801268889422113,
            "velocity": 29.85039166885911,
            "ew_lambda": 2655.028638137306,
            "ns_lambda": 2074.0355202843975,
            "ew_r2": 0.9798116050358113,
            "ns_r2": 0.9527739579531633,
            "n_ew_pairs": 167537,
            "n_ns_pairs": 185897
          },
          "2023-11": {
            "year": 2023,
            "month": 11,
            "ratio": 1.3280649645483942,
            "velocity": 30.084307016397368,
            "ew_lambda": 2440.7164020069313,
            "ns_lambda": 1837.7989534848487,
            "ew_r2": 0.9684712328924088,
            "ns_r2": 0.9582579422852869,
            "n_ew_pairs": 165621,
            "n_ns_pairs": 173832
          },
          "2023-12": {
            "year": 2023,
            "month": 12,
            "ratio": 1.1270090766347258,
            "velocity": 30.23885263626665,
            "ew_lambda": 2175.03975913549,
            "ns_lambda": 1929.92213126642,
            "ew_r2": 0.9281082560675532,
            "ns_r2": 0.9180411231200262,
            "n_ew_pairs": 197472,
            "n_ns_pairs": 198009
          },
          "2024-01": {
            "year": 2024,
            "month": 1,
            "ratio": 0.8475601522732218,
            "velocity": 30.266810382445737,
            "ew_lambda": 2272.7541289146166,
            "ns_lambda": 2681.5254620205,
            "ew_r2": 0.9432961673743958,
            "ns_r2": 0.9713301503239054,
            "n_ew_pairs": 194246,
            "n_ns_pairs": 200879
          },
          "2024-02": {
            "year": 2024,
            "month": 2,
            "ratio": 1.0334290851535124,
            "velocity": 30.15355743865211,
            "ew_lambda": 1802.9510328454676,
            "ns_lambda": 1744.6296594000403,
            "ew_r2": 0.9245982938639548,
            "ns_r2": 0.9391314450089565,
            "n_ew_pairs": 153543,
            "n_ns_pairs": 170161
          },
          "2024-03": {
            "year": 2024,
            "month": 3,
            "ratio": 0.9478486860476971,
            "velocity": 29.94339266862619,
            "ew_lambda": 1587.874700730197,
            "ns_lambda": 1675.2407046648507,
            "ew_r2": 0.899132272423251,
            "ns_r2": 0.9578934901911558,
            "n_ew_pairs": 161469,
            "n_ns_pairs": 172588
          },
          "2024-04": {
            "year": 2024,
            "month": 4,
            "ratio": 1.1375437709539429,
            "velocity": 29.69083901734369,
            "ew_lambda": 1717.140613302598,
            "ns_lambda": 1509.5160794231292,
            "ew_r2": 0.8938390987443711,
            "ns_r2": 0.9071425334128875,
            "n_ew_pairs": 160233,
            "n_ns_pairs": 177134
          },
          "2024-05": {
            "year": 2024,
            "month": 5,
            "ratio": 0.8186867907334777,
            "velocity": 29.46141635681075,
            "ew_lambda": 1738.7697719717867,
            "ns_lambda": 2123.8522370856726,
            "ew_r2": 0.9213139862630689,
            "ns_r2": 0.9558458201114615,
            "n_ew_pairs": 208329,
            "n_ns_pairs": 230084
          },
          "2024-06": {
            "year": 2024,
            "month": 6,
            "ratio": 0.7736699005151348,
            "velocity": 29.31464369725387,
            "ew_lambda": 1898.4617492525583,
            "ns_lambda": 2453.839483723614,
            "ew_r2": 0.9281465490530517,
            "ns_r2": 0.9608432156678332,
            "n_ew_pairs": 230119,
            "n_ns_pairs": 240497
          },
          "2024-07": {
            "year": 2024,
            "month": 7,
            "ratio": 0.9295806360552218,
            "velocity": 29.288598198988613,
            "ew_lambda": 1618.801668744216,
            "ns_lambda": 1741.4322178802904,
            "ew_r2": 0.9521977341555095,
            "ns_r2": 0.95290668198393,
            "n_ew_pairs": 215763,
            "n_ns_pairs": 225300
          },
          "2024-08": {
            "year": 2024,
            "month": 8,
            "ratio": 1.1114635603103395,
            "velocity": 29.390036833074433,
            "ew_lambda": 1714.2205942630333,
            "ns_lambda": 1542.3093077243068,
            "ew_r2": 0.9207177593307432,
            "ns_r2": 0.9402294833902994,
            "n_ew_pairs": 181858,
            "n_ns_pairs": 203179
          },
          "2024-09": {
            "year": 2024,
            "month": 9,
            "ratio": 0.9813466028711163,
            "velocity": 29.59264342356999,
            "ew_lambda": 1769.607910743532,
            "ns_lambda": 1803.2445474068054,
            "ew_r2": 0.9492175335733859,
            "ns_r2": 0.9736697682587384,
            "n_ew_pairs": 163372,
            "n_ns_pairs": 180185
          },
          "2024-10": {
            "year": 2024,
            "month": 10,
            "ratio": 0.8239600872686191,
            "velocity": 29.843855840371614,
            "ew_lambda": 1691.7473162989047,
            "ns_lambda": 2053.1908552839627,
            "ew_r2": 0.9546803907731793,
            "ns_r2": 0.9711868394525184,
            "n_ew_pairs": 151691,
            "n_ns_pairs": 166234
          },
          "2024-11": {
            "year": 2024,
            "month": 11,
            "ratio": 0.9168584041970979,
            "velocity": 30.078502167287997,
            "ew_lambda": 1986.9282124223503,
            "ns_lambda": 2167.104760480789,
            "ew_r2": 0.9347467805200972,
            "ns_r2": 0.9625274210408208,
            "n_ew_pairs": 135051,
            "n_ns_pairs": 139551
          },
          "2024-12": {
            "year": 2024,
            "month": 12,
            "ratio": 0.8436276008477974,
            "velocity": 30.235708220840905,
            "ew_lambda": 1605.4622124749367,
            "ns_lambda": 1903.0460962414447,
            "ew_r2": 0.838685883415375,
            "ns_r2": 0.9071635609415937,
            "n_ew_pairs": 191153,
            "n_ns_pairs": 197283
          }
        },
        "correlation": {
          "pearson_r": -0.40088681133066995,
          "p_value": 0.015391375112440975,
          "monte_carlo_p": 0.016698330166983303,
          "sigma": 2.4230366189706647,
          "n_months": 36,
          "n_surrogates": 10000
        },
        "seasonal_analysis": {
          "equinox_mean_ratio": 1.0994245966291718,
          "solstice_mean_ratio": 1.018844155586888,
          "seasonal_contrast": 1.0790900557267926,
          "n_equinox_months": 12,
          "n_solstice_months": 12,
          "modulation_detected": false
        },
        "n_months": 36
      }
    },
    "clock_drift": {
      "msc": {
        "monthly_anisotropy": {
          "2022-01": {
            "year": 2022,
            "month": 1,
            "ratio": 1.055253411299242,
            "velocity": 30.266752889009627,
            "ew_lambda": 606.646023266294,
            "ns_lambda": 574.8818404854843,
            "ew_r2": 0.9534848942376275,
            "ns_r2": 0.9765014856653506,
            "n_ew_pairs": 186899,
            "n_ns_pairs": 192012
          },
          "2022-02": {
            "year": 2022,
            "month": 2,
            "ratio": 1.0219173998904048,
            "velocity": 30.152908164805467,
            "ew_lambda": 654.7435405968374,
            "ns_lambda": 640.7010396995444,
            "ew_r2": 0.9610479612429659,
            "ns_r2": 0.9731623494072029,
            "n_ew_pairs": 157869,
            "n_ns_pairs": 166222
          },
          "2022-03": {
            "year": 2022,
            "month": 3,
            "ratio": 1.2138320640120088,
            "velocity": 29.941801077621474,
            "ew_lambda": 799.6246118469236,
            "ns_lambda": 658.7604954213936,
            "ew_r2": 0.9588098348817706,
            "ns_r2": 0.9620213119682538,
            "n_ew_pairs": 191744,
            "n_ns_pairs": 193856
          },
          "2022-04": {
            "year": 2022,
            "month": 4,
            "ratio": 1.2736191022658359,
            "velocity": 29.688492835763494,
            "ew_lambda": 829.822926147882,
            "ns_lambda": 651.5471734615028,
            "ew_r2": 0.9376971026850865,
            "ns_r2": 0.9048512633714139,
            "n_ew_pairs": 179335,
            "n_ns_pairs": 187021
          },
          "2022-05": {
            "year": 2022,
            "month": 5,
            "ratio": 1.0942639629987863,
            "velocity": 29.459051604240003,
            "ew_lambda": 715.5380153794615,
            "ns_lambda": 653.8989124877679,
            "ew_r2": 0.9508339808952536,
            "ns_r2": 0.9259256937045253,
            "n_ew_pairs": 185511,
            "n_ns_pairs": 207682
          },
          "2022-06": {
            "year": 2022,
            "month": 6,
            "ratio": 0.992947377462468,
            "velocity": 29.31332052527508,
            "ew_lambda": 801.5833741800079,
            "ns_lambda": 807.2767926821043,
            "ew_r2": 0.970822491702587,
            "ns_r2": 0.9595808384592387,
            "n_ew_pairs": 258765,
            "n_ns_pairs": 262049
          },
          "2022-07": {
            "year": 2022,
            "month": 7,
            "ratio": 1.1262524425864764,
            "velocity": 29.289309356866724,
            "ew_lambda": 921.3466858121479,
            "ns_lambda": 818.0640955559169,
            "ew_r2": 0.962244640529169,
            "ns_r2": 0.9695943356957935,
            "n_ew_pairs": 206095,
            "n_ns_pairs": 211006
          },
          "2022-08": {
            "year": 2022,
            "month": 8,
            "ratio": 1.2521898541162688,
            "velocity": 29.393280721284196,
            "ew_lambda": 994.6380804450063,
            "ns_lambda": 794.318910327676,
            "ew_r2": 0.9597502291413753,
            "ns_r2": 0.9643180008788592,
            "n_ew_pairs": 206793,
            "n_ns_pairs": 213789
          },
          "2022-09": {
            "year": 2022,
            "month": 9,
            "ratio": 1.3432992162521544,
            "velocity": 29.598116680279198,
            "ew_lambda": 859.3575934315983,
            "ns_lambda": 639.7365404777291,
            "ew_r2": 0.9586763113422494,
            "ns_r2": 0.9751098637750855,
            "n_ew_pairs": 196629,
            "n_ns_pairs": 204525
          },
          "2022-10": {
            "year": 2022,
            "month": 10,
            "ratio": 1.2422362296308986,
            "velocity": 29.85039166885911,
            "ew_lambda": 754.3841806174293,
            "ns_lambda": 607.2791652853152,
            "ew_r2": 0.9604488450841954,
            "ns_r2": 0.949195790952759,
            "n_ew_pairs": 176817,
            "n_ns_pairs": 193359
          },
          "2022-11": {
            "year": 2022,
            "month": 11,
            "ratio": 1.2556305622151978,
            "velocity": 30.084307016397368,
            "ew_lambda": 722.1011607374154,
            "ns_lambda": 575.0904624872114,
            "ew_r2": 0.9643191571845877,
            "ns_r2": 0.9685443053406736,
            "n_ew_pairs": 176894,
            "n_ns_pairs": 185830
          },
          "2022-12": {
            "year": 2022,
            "month": 12,
            "ratio": 0.9066305436178111,
            "velocity": 30.23885263626665,
            "ew_lambda": 717.748798184681,
            "ns_lambda": 791.6662451284534,
            "ew_r2": 0.9614532429884022,
            "ns_r2": 0.9523408568739422,
            "n_ew_pairs": 180852,
            "n_ns_pairs": 185246
          },
          "2023-01": {
            "year": 2023,
            "month": 1,
            "ratio": 0.8501993860225009,
            "velocity": 30.266752889009627,
            "ew_lambda": 773.1771678744776,
            "ns_lambda": 909.4068762995028,
            "ew_r2": 0.9599023396605596,
            "ns_r2": 0.940704487117847,
            "n_ew_pairs": 174368,
            "n_ns_pairs": 177259
          },
          "2023-02": {
            "year": 2023,
            "month": 2,
            "ratio": 1.1155666986567974,
            "velocity": 30.152908164805467,
            "ew_lambda": 653.8365136119957,
            "ns_lambda": 586.1025740542902,
            "ew_r2": 0.9613479221498047,
            "ns_r2": 0.9567911666580544,
            "n_ew_pairs": 155946,
            "n_ns_pairs": 163652
          },
          "2023-03": {
            "year": 2023,
            "month": 3,
            "ratio": 1.37655134796278,
            "velocity": 29.941801077621474,
            "ew_lambda": 734.5142382018671,
            "ns_lambda": 533.5901485178215,
            "ew_r2": 0.9683598426417505,
            "ns_r2": 0.9630065449624589,
            "n_ew_pairs": 149067,
            "n_ns_pairs": 167098
          },
          "2023-04": {
            "year": 2023,
            "month": 4,
            "ratio": 1.1982005551113835,
            "velocity": 29.688492835763494,
            "ew_lambda": 722.616286614246,
            "ns_lambda": 603.0845867427196,
            "ew_r2": 0.9691731873220366,
            "ns_r2": 0.942142084774084,
            "n_ew_pairs": 160574,
            "n_ns_pairs": 174909
          },
          "2023-05": {
            "year": 2023,
            "month": 5,
            "ratio": 1.3010524083947186,
            "velocity": 29.459051604240003,
            "ew_lambda": 879.1737553943734,
            "ns_lambda": 675.7404618920209,
            "ew_r2": 0.9551087944275035,
            "ns_r2": 0.9505204777332114,
            "n_ew_pairs": 194088,
            "n_ns_pairs": 195004
          },
          "2023-06": {
            "year": 2023,
            "month": 6,
            "ratio": 1.1408735493872237,
            "velocity": 29.31332052527508,
            "ew_lambda": 812.8442027781591,
            "ns_lambda": 712.4752810815423,
            "ew_r2": 0.9595077493076087,
            "ns_r2": 0.9687714603237069,
            "n_ew_pairs": 205395,
            "n_ns_pairs": 209179
          },
          "2023-07": {
            "year": 2023,
            "month": 7,
            "ratio": 1.2931897964608408,
            "velocity": 29.289309356866724,
            "ew_lambda": 1176.44567588423,
            "ns_lambda": 909.7239083573717,
            "ew_r2": 0.951455070759322,
            "ns_r2": 0.9708311604580993,
            "n_ew_pairs": 213008,
            "n_ns_pairs": 214576
          },
          "2023-08": {
            "year": 2023,
            "month": 8,
            "ratio": 1.3620639987336778,
            "velocity": 29.393280721284196,
            "ew_lambda": 965.8279925429568,
            "ns_lambda": 709.0914916192596,
            "ew_r2": 0.963981835659988,
            "ns_r2": 0.9703306577836086,
            "n_ew_pairs": 198275,
            "n_ns_pairs": 203089
          },
          "2023-09": {
            "year": 2023,
            "month": 9,
            "ratio": 1.240395661841525,
            "velocity": 29.598116680279198,
            "ew_lambda": 814.671631611254,
            "ns_lambda": 656.7836833625897,
            "ew_r2": 0.9826275160017858,
            "ns_r2": 0.9693801591209223,
            "n_ew_pairs": 177003,
            "n_ns_pairs": 191794
          },
          "2023-10": {
            "year": 2023,
            "month": 10,
            "ratio": 1.321328725987268,
            "velocity": 29.85039166885911,
            "ew_lambda": 803.5527934704406,
            "ns_lambda": 608.1399561415299,
            "ew_r2": 0.9737095148752156,
            "ns_r2": 0.9738410301687163,
            "n_ew_pairs": 167537,
            "n_ns_pairs": 185897
          },
          "2023-11": {
            "year": 2023,
            "month": 11,
            "ratio": 1.1487736652482459,
            "velocity": 30.084307016397368,
            "ew_lambda": 732.2332218331477,
            "ns_lambda": 637.4042546274028,
            "ew_r2": 0.9590166093396346,
            "ns_r2": 0.949291321802231,
            "n_ew_pairs": 165621,
            "n_ns_pairs": 173832
          },
          "2023-12": {
            "year": 2023,
            "month": 12,
            "ratio": 0.8441313147597768,
            "velocity": 30.23885263626665,
            "ew_lambda": 680.5059908893681,
            "ns_lambda": 806.1612914846393,
            "ew_r2": 0.9613473968688322,
            "ns_r2": 0.9651492285779046,
            "n_ew_pairs": 197472,
            "n_ns_pairs": 198009
          },
          "2024-01": {
            "year": 2024,
            "month": 1,
            "ratio": 0.5698441256586947,
            "velocity": 30.266810382445737,
            "ew_lambda": 741.1556532104569,
            "ns_lambda": 1300.6287506320077,
            "ew_r2": 0.9691854455475214,
            "ns_r2": 0.8875943755456802,
            "n_ew_pairs": 194246,
            "n_ns_pairs": 200879
          },
          "2024-02": {
            "year": 2024,
            "month": 2,
            "ratio": 1.0517798165841419,
            "velocity": 30.15355743865211,
            "ew_lambda": 909.6890203983241,
            "ns_lambda": 864.9044277657988,
            "ew_r2": 0.9412742003155974,
            "ns_r2": 0.8121983451053355,
            "n_ew_pairs": 153543,
            "n_ns_pairs": 170161
          },
          "2024-03": {
            "year": 2024,
            "month": 3,
            "ratio": 1.5575575075818922,
            "velocity": 29.94339266862619,
            "ew_lambda": 1010.4112041302445,
            "ns_lambda": 648.7151833635394,
            "ew_r2": 0.906995309370755,
            "ns_r2": 0.8069542882737639,
            "n_ew_pairs": 161469,
            "n_ns_pairs": 172588
          },
          "2024-04": {
            "year": 2024,
            "month": 4,
            "ratio": 1.5324168720044198,
            "velocity": 29.69083901734369,
            "ew_lambda": 967.9822532824694,
            "ns_lambda": 631.670318283782,
            "ew_r2": 0.9103449561612855,
            "ns_r2": 0.8767421559908749,
            "n_ew_pairs": 160233,
            "n_ns_pairs": 177134
          },
          "2024-05": {
            "year": 2024,
            "month": 5,
            "ratio": 1.1802788875535768,
            "velocity": 29.46141635681075,
            "ew_lambda": 685.7837401298082,
            "ns_lambda": 581.0353361071013,
            "ew_r2": 0.9327160297145338,
            "ns_r2": 0.9285166842423082,
            "n_ew_pairs": 208329,
            "n_ns_pairs": 230084
          },
          "2024-06": {
            "year": 2024,
            "month": 6,
            "ratio": 0.9389960613952054,
            "velocity": 29.31464369725387,
            "ew_lambda": 646.2584131445091,
            "ns_lambda": 688.2440083766351,
            "ew_r2": 0.9371767620228568,
            "ns_r2": 0.9510815137669695,
            "n_ew_pairs": 230119,
            "n_ns_pairs": 240497
          },
          "2024-07": {
            "year": 2024,
            "month": 7,
            "ratio": 1.0865902060505428,
            "velocity": 29.288598198988613,
            "ew_lambda": 769.524932120061,
            "ns_lambda": 708.2016088816712,
            "ew_r2": 0.9353541953881588,
            "ns_r2": 0.9477526376068341,
            "n_ew_pairs": 215763,
            "n_ns_pairs": 225300
          },
          "2024-08": {
            "year": 2024,
            "month": 8,
            "ratio": 1.2160533036397423,
            "velocity": 29.390036833074433,
            "ew_lambda": 833.0856724665684,
            "ns_lambda": 685.0733187213735,
            "ew_r2": 0.9529328503295269,
            "ns_r2": 0.90545116306267,
            "n_ew_pairs": 181858,
            "n_ns_pairs": 203179
          },
          "2024-09": {
            "year": 2024,
            "month": 9,
            "ratio": 1.3887616494449595,
            "velocity": 29.59264342356999,
            "ew_lambda": 693.5166427626366,
            "ns_lambda": 499.3777319814465,
            "ew_r2": 0.966464195659219,
            "ns_r2": 0.9237339768121492,
            "n_ew_pairs": 163372,
            "n_ns_pairs": 180185
          },
          "2024-10": {
            "year": 2024,
            "month": 10,
            "ratio": 1.4036252222224022,
            "velocity": 29.843855840371614,
            "ew_lambda": 862.9479870841124,
            "ns_lambda": 614.79943037628,
            "ew_r2": 0.9401685009729714,
            "ns_r2": 0.9260962289250438,
            "n_ew_pairs": 151691,
            "n_ns_pairs": 166234
          },
          "2024-11": {
            "year": 2024,
            "month": 11,
            "ratio": 1.3674013732274013,
            "velocity": 30.078502167287997,
            "ew_lambda": 985.8742463148811,
            "ns_lambda": 720.9838059383961,
            "ew_r2": 0.9293969657456822,
            "ns_r2": 0.9206149387422828,
            "n_ew_pairs": 135051,
            "n_ns_pairs": 139551
          },
          "2024-12": {
            "year": 2024,
            "month": 12,
            "ratio": 0.8933728064614678,
            "velocity": 30.235708220840905,
            "ew_lambda": 762.6590128394014,
            "ns_lambda": 853.6850543505947,
            "ew_r2": 0.9307820043938065,
            "ns_r2": 0.826809719921154,
            "n_ew_pairs": 191153,
            "n_ns_pairs": 197283
          }
        },
        "correlation": {
          "pearson_r": -0.34205938513642253,
          "p_value": 0.041153285151926865,
          "monte_carlo_p": 0.044995500449955005,
          "sigma": 2.0419823196731346,
          "n_months": 36,
          "n_surrogates": 10000
        },
        "seasonal_analysis": {
          "equinox_mean_ratio": 1.3409853461931274,
          "solstice_mean_ratio": 0.9748567517635207,
          "seasonal_contrast": 1.3755716865757746,
          "n_equinox_months": 12,
          "n_solstice_months": 12,
          "modulation_detected": true
        },
        "n_months": 36
      },
      "phase_alignment": {
        "monthly_anisotropy": {
          "2022-01": {
            "year": 2022,
            "month": 1,
            "ratio": 0.7907369217644757,
            "velocity": 30.266752889009627,
            "ew_lambda": 827.4074782647043,
            "ns_lambda": 1046.3751666210308,
            "ew_r2": 0.9564748145730272,
            "ns_r2": 0.951944260005372,
            "n_ew_pairs": 186899,
            "n_ns_pairs": 192012
          },
          "2022-02": {
            "year": 2022,
            "month": 2,
            "ratio": 0.9535454540026055,
            "velocity": 30.152908164805467,
            "ew_lambda": 936.5295306629363,
            "ns_lambda": 982.1550999291716,
            "ew_r2": 0.9457877717524269,
            "ns_r2": 0.9132720371836649,
            "n_ew_pairs": 157869,
            "n_ns_pairs": 166222
          },
          "2022-03": {
            "year": 2022,
            "month": 3,
            "ratio": 1.1022143548089214,
            "velocity": 29.941801077621474,
            "ew_lambda": 1051.6664330561853,
            "ns_lambda": 954.1396630045714,
            "ew_r2": 0.9598543006293155,
            "ns_r2": 0.9130019395045381,
            "n_ew_pairs": 191744,
            "n_ns_pairs": 193856
          },
          "2022-04": {
            "year": 2022,
            "month": 4,
            "ratio": 1.323950043524458,
            "velocity": 29.688492835763494,
            "ew_lambda": 1147.269522098531,
            "ns_lambda": 866.550462164275,
            "ew_r2": 0.9623122485533544,
            "ns_r2": 0.8996934205395783,
            "n_ew_pairs": 179335,
            "n_ns_pairs": 187021
          },
          "2022-05": {
            "year": 2022,
            "month": 5,
            "ratio": 1.0532909078943429,
            "velocity": 29.459051604240003,
            "ew_lambda": 990.4809803874564,
            "ns_lambda": 940.3679201670399,
            "ew_r2": 0.9542771696530947,
            "ns_r2": 0.8752935359859537,
            "n_ew_pairs": 185511,
            "n_ns_pairs": 207682
          },
          "2022-06": {
            "year": 2022,
            "month": 6,
            "ratio": 0.9725374546754607,
            "velocity": 29.31332052527508,
            "ew_lambda": 1009.3326043060546,
            "ns_lambda": 1037.834172302261,
            "ew_r2": 0.9519455854306451,
            "ns_r2": 0.9182705656103763,
            "n_ew_pairs": 258765,
            "n_ns_pairs": 262049
          },
          "2022-07": {
            "year": 2022,
            "month": 7,
            "ratio": 1.0569198090879617,
            "velocity": 29.289309356866724,
            "ew_lambda": 1103.4334319853256,
            "ns_lambda": 1044.0086584596247,
            "ew_r2": 0.9468355185411924,
            "ns_r2": 0.9138545685613231,
            "n_ew_pairs": 206095,
            "n_ns_pairs": 211006
          },
          "2022-08": {
            "year": 2022,
            "month": 8,
            "ratio": 1.2650407757497142,
            "velocity": 29.393280721284196,
            "ew_lambda": 1168.9671160076405,
            "ns_lambda": 924.0548908906619,
            "ew_r2": 0.9316549198249887,
            "ns_r2": 0.8953411810440276,
            "n_ew_pairs": 206793,
            "n_ns_pairs": 213789
          },
          "2022-09": {
            "year": 2022,
            "month": 9,
            "ratio": 1.096616204009019,
            "velocity": 29.598116680279198,
            "ew_lambda": 1020.831293461697,
            "ns_lambda": 930.8920383719784,
            "ew_r2": 0.9139930635549945,
            "ns_r2": 0.9232273466096143,
            "n_ew_pairs": 196629,
            "n_ns_pairs": 204525
          },
          "2022-10": {
            "year": 2022,
            "month": 10,
            "ratio": 0.9611244159683556,
            "velocity": 29.85039166885911,
            "ew_lambda": 988.3920788974556,
            "ns_lambda": 1028.3705860303498,
            "ew_r2": 0.9590740523838841,
            "ns_r2": 0.9688581406242063,
            "n_ew_pairs": 176817,
            "n_ns_pairs": 193359
          },
          "2022-11": {
            "year": 2022,
            "month": 11,
            "ratio": 1.2259908257455248,
            "velocity": 30.084307016397368,
            "ew_lambda": 1004.1353856531142,
            "ns_lambda": 819.0398855900897,
            "ew_r2": 0.9514942169616275,
            "ns_r2": 0.9488714291850787,
            "n_ew_pairs": 176894,
            "n_ns_pairs": 185830
          },
          "2022-12": {
            "year": 2022,
            "month": 12,
            "ratio": 1.1378090950146345,
            "velocity": 30.23885263626665,
            "ew_lambda": 936.267402799026,
            "ns_lambda": 822.8686226022685,
            "ew_r2": 0.9457098609546787,
            "ns_r2": 0.8964901589706461,
            "n_ew_pairs": 180852,
            "n_ns_pairs": 185246
          },
          "2023-01": {
            "year": 2023,
            "month": 1,
            "ratio": 0.7934654853362508,
            "velocity": 30.266752889009627,
            "ew_lambda": 908.9925978304994,
            "ns_lambda": 1145.5981572346416,
            "ew_r2": 0.9621326224506264,
            "ns_r2": 0.9384493161305274,
            "n_ew_pairs": 174368,
            "n_ns_pairs": 177259
          },
          "2023-02": {
            "year": 2023,
            "month": 2,
            "ratio": 0.9094174215935059,
            "velocity": 30.152908164805467,
            "ew_lambda": 901.144278175396,
            "ns_lambda": 990.902809621116,
            "ew_r2": 0.9520722585183418,
            "ns_r2": 0.9256934210604354,
            "n_ew_pairs": 155946,
            "n_ns_pairs": 163652
          },
          "2023-03": {
            "year": 2023,
            "month": 3,
            "ratio": 1.0012732966781899,
            "velocity": 29.941801077621474,
            "ew_lambda": 900.8170032836405,
            "ns_lambda": 899.6714546090246,
            "ew_r2": 0.9394026187907291,
            "ns_r2": 0.8875579525167954,
            "n_ew_pairs": 149067,
            "n_ns_pairs": 167098
          },
          "2023-04": {
            "year": 2023,
            "month": 4,
            "ratio": 1.1191925974971937,
            "velocity": 29.688492835763494,
            "ew_lambda": 1043.4133986243119,
            "ns_lambda": 932.291190057597,
            "ew_r2": 0.9374604938043027,
            "ns_r2": 0.8685705820441728,
            "n_ew_pairs": 160574,
            "n_ns_pairs": 174909
          },
          "2023-05": {
            "year": 2023,
            "month": 5,
            "ratio": 1.0389678871705241,
            "velocity": 29.459051604240003,
            "ew_lambda": 1057.802108465549,
            "ns_lambda": 1018.1278185087291,
            "ew_r2": 0.9176956705547689,
            "ns_r2": 0.9133622109286901,
            "n_ew_pairs": 194088,
            "n_ns_pairs": 195004
          },
          "2023-06": {
            "year": 2023,
            "month": 6,
            "ratio": 0.8412721713811093,
            "velocity": 29.31332052527508,
            "ew_lambda": 883.7602183543293,
            "ns_lambda": 1050.5045197245354,
            "ew_r2": 0.9208531675983931,
            "ns_r2": 0.9017694264778866,
            "n_ew_pairs": 205395,
            "n_ns_pairs": 209179
          },
          "2023-07": {
            "year": 2023,
            "month": 7,
            "ratio": 0.938245311208732,
            "velocity": 29.289309356866724,
            "ew_lambda": 919.1583595852804,
            "ns_lambda": 979.6567577845265,
            "ew_r2": 0.9400519041105557,
            "ns_r2": 0.9074035120212552,
            "n_ew_pairs": 213008,
            "n_ns_pairs": 214576
          },
          "2023-08": {
            "year": 2023,
            "month": 8,
            "ratio": 1.0042946931392631,
            "velocity": 29.393280721284196,
            "ew_lambda": 977.9567173553338,
            "ns_lambda": 973.774654029485,
            "ew_r2": 0.9530931954974985,
            "ns_r2": 0.9092448470612255,
            "n_ew_pairs": 198275,
            "n_ns_pairs": 203089
          },
          "2023-09": {
            "year": 2023,
            "month": 9,
            "ratio": 0.8925878089939754,
            "velocity": 29.598116680279198,
            "ew_lambda": 853.2550595483297,
            "ns_lambda": 955.9340279473712,
            "ew_r2": 0.9496139790043078,
            "ns_r2": 0.9505107326250326,
            "n_ew_pairs": 177003,
            "n_ns_pairs": 191794
          },
          "2023-10": {
            "year": 2023,
            "month": 10,
            "ratio": 1.0273726136552122,
            "velocity": 29.85039166885911,
            "ew_lambda": 922.1673110292464,
            "ns_lambda": 897.5977155438633,
            "ew_r2": 0.9487670311627469,
            "ns_r2": 0.9347700138786456,
            "n_ew_pairs": 167537,
            "n_ns_pairs": 185897
          },
          "2023-11": {
            "year": 2023,
            "month": 11,
            "ratio": 0.9893509130019654,
            "velocity": 30.084307016397368,
            "ew_lambda": 972.3956172059079,
            "ns_lambda": 982.8622023053373,
            "ew_r2": 0.9583981496077869,
            "ns_r2": 0.922892325449723,
            "n_ew_pairs": 165621,
            "n_ns_pairs": 173832
          },
          "2023-12": {
            "year": 2023,
            "month": 12,
            "ratio": 0.722356791641159,
            "velocity": 30.23885263626665,
            "ew_lambda": 942.8715521328254,
            "ns_lambda": 1305.271249669665,
            "ew_r2": 0.934370536527653,
            "ns_r2": 0.9433534274458621,
            "n_ew_pairs": 197472,
            "n_ns_pairs": 198009
          },
          "2024-01": {
            "year": 2024,
            "month": 1,
            "ratio": 0.8401969644713723,
            "velocity": 30.266810382445737,
            "ew_lambda": 848.4571213660819,
            "ns_lambda": 1009.8312148746058,
            "ew_r2": 0.928445353785905,
            "ns_r2": 0.9253864991710073,
            "n_ew_pairs": 194246,
            "n_ns_pairs": 200879
          },
          "2024-02": {
            "year": 2024,
            "month": 2,
            "ratio": 1.042543551610754,
            "velocity": 30.15355743865211,
            "ew_lambda": 1013.1264264303578,
            "ns_lambda": 971.7833129033833,
            "ew_r2": 0.9349038373830824,
            "ns_r2": 0.9356672745297777,
            "n_ew_pairs": 153543,
            "n_ns_pairs": 170161
          },
          "2024-03": {
            "year": 2024,
            "month": 3,
            "ratio": 0.9301388651242024,
            "velocity": 29.94339266862619,
            "ew_lambda": 787.7566157774847,
            "ns_lambda": 846.923664105031,
            "ew_r2": 0.9252478064746692,
            "ns_r2": 0.9365221709899398,
            "n_ew_pairs": 161469,
            "n_ns_pairs": 172588
          },
          "2024-04": {
            "year": 2024,
            "month": 4,
            "ratio": 0.8732794297601433,
            "velocity": 29.69083901734369,
            "ew_lambda": 852.268340410434,
            "ns_lambda": 975.9400157227107,
            "ew_r2": 0.9204408888590273,
            "ns_r2": 0.9245074184421351,
            "n_ew_pairs": 160233,
            "n_ns_pairs": 177134
          },
          "2024-05": {
            "year": 2024,
            "month": 5,
            "ratio": 0.6765399949795802,
            "velocity": 29.46141635681075,
            "ew_lambda": 715.1654469210929,
            "ns_lambda": 1057.0926363971705,
            "ew_r2": 0.937051644876769,
            "ns_r2": 0.926836852444605,
            "n_ew_pairs": 208329,
            "n_ns_pairs": 230084
          },
          "2024-06": {
            "year": 2024,
            "month": 6,
            "ratio": 0.6609245069522613,
            "velocity": 29.31464369725387,
            "ew_lambda": 729.7270319813834,
            "ns_lambda": 1104.1004294823217,
            "ew_r2": 0.9105788790364131,
            "ns_r2": 0.9235137549018223,
            "n_ew_pairs": 230119,
            "n_ns_pairs": 240497
          },
          "2024-07": {
            "year": 2024,
            "month": 7,
            "ratio": 0.914793353598333,
            "velocity": 29.288598198988613,
            "ew_lambda": 856.7993210141315,
            "ns_lambda": 936.6042261281387,
            "ew_r2": 0.9590808748913515,
            "ns_r2": 0.8967273963455249,
            "n_ew_pairs": 215763,
            "n_ns_pairs": 225300
          },
          "2024-08": {
            "year": 2024,
            "month": 8,
            "ratio": 1.4040388521975444,
            "velocity": 29.390036833074433,
            "ew_lambda": 953.3346304391134,
            "ns_lambda": 678.9944800651299,
            "ew_r2": 0.9675714901177935,
            "ns_r2": 0.9127319848044191,
            "n_ew_pairs": 181858,
            "n_ns_pairs": 203179
          },
          "2024-09": {
            "year": 2024,
            "month": 9,
            "ratio": 1.429477174126156,
            "velocity": 29.59264342356999,
            "ew_lambda": 889.7217508479215,
            "ns_lambda": 622.4106036473169,
            "ew_r2": 0.9669032841536928,
            "ns_r2": 0.9022438097129487,
            "n_ew_pairs": 163372,
            "n_ns_pairs": 180185
          },
          "2024-10": {
            "year": 2024,
            "month": 10,
            "ratio": 1.1080113958175641,
            "velocity": 29.843855840371614,
            "ew_lambda": 914.0561696015791,
            "ns_lambda": 824.9519572198335,
            "ew_r2": 0.9586500326101237,
            "ns_r2": 0.9386891614557471,
            "n_ew_pairs": 151691,
            "n_ns_pairs": 166234
          },
          "2024-11": {
            "year": 2024,
            "month": 11,
            "ratio": 0.9529330560794624,
            "velocity": 30.078502167287997,
            "ew_lambda": 871.8605661750905,
            "ns_lambda": 914.9232053740284,
            "ew_r2": 0.969797313752121,
            "ns_r2": 0.936923125359219,
            "n_ew_pairs": 135051,
            "n_ns_pairs": 139551
          },
          "2024-12": {
            "year": 2024,
            "month": 12,
            "ratio": 0.9231379830409546,
            "velocity": 30.235708220840905,
            "ew_lambda": 856.0463719342038,
            "ns_lambda": 927.3222288116225,
            "ew_r2": 0.9685531219978812,
            "ns_r2": 0.9489821166188269,
            "n_ew_pairs": 191153,
            "n_ns_pairs": 197283
          }
        },
        "correlation": {
          "pearson_r": -0.16011544826711577,
          "p_value": 0.3509099513980597,
          "monte_carlo_p": 0.35206479352064796,
          "sigma": 0.9328257352243231,
          "n_months": 36,
          "n_surrogates": 10000
        },
        "seasonal_analysis": {
          "equinox_mean_ratio": 1.0721031833302828,
          "solstice_mean_ratio": 0.882699654014392,
          "seasonal_contrast": 1.2145730186417436,
          "n_equinox_months": 12,
          "n_solstice_months": 12,
          "modulation_detected": true
        },
        "n_months": 36
      }
    }
  },
  "timestamp": "2025-12-17T21:38:24.536944"
}